[{"id":788,"type":"movie","title":"Final Destination 5","description":"Horror ကားကြိုက်နှစ်သက်သူတို့အဖို့  ကြည့်ဖူးသမျှထဲမယ် သူတို့ရဲ့ နှလုံးသည်းအူကို လှုပ်ရမ်းနိုင်တဲ့ ဇာတ်ကားများကို ပြောပါဆိုရင်Final Destination တွေကိုပြောကြမှာသေချာသလောက်ပါပဲ….ယ္ခုနောက်ပိုင်းထွက်တဲ့ horror ကားတော်တော်များများမှာ အထူးသဖြင့် Jump scare မျိုး ဝုန်းကနဲ\r\nဒိုင်းခနဲ ခြောက်လှန့်တတ်တဲ့ ကားမျိုးတွေကို horror ကား ကြိုက်နှစ်သက်သူသူတို့အဖို့ ကြာလာတော့ အနည်းငယ်ရိုးအီလာသလိုပါပဲ…….Final Destination လို horror မျိုးကျတော့လည်း တကယ့်ကို သွေးပျက်ထိတ်လန့်စရာဖြစ်တဲ့အပြင်ကျောထဲစိမ့်နေအောင် ကြောက်နေရတာမျိုး….မင်း horror ဘယ်လောက် crazy ဖြစ်လဲဆိုတာကို Final Destination (1 to 5)ကို စဆုံးကြည့်ဖြစ်လားဆိုတာမျိုးနဲ့ ဆုံးဖြတ်ရလောက်အောင် သွေးပျက်ထိတ်လန့်စရာပါပဲ…","year":2011,"imdb":5.8,"comment":true,"rating":0,"duration":"92 min","downloadas":"1","playas":"1","classification":"860 MB","image":"https://app.zchannelmovie.com/uploads/cache/poster_thumb/uploads/jpg/ea225abb7475805e21cad96d475d9aee.jpg","genres":[{"id":5,"title":"Horror & Thriller"}],"trailer":{"id":4790,"type":"youtube","url":"https://youtu.be/g7V84i92H4A"},"sources":[{"id":4789,"type":"mp4","url":"https://f002.backblazeb2.com/file/zstorage501/movies/Final.Destination/Final.Destination.5.2011.(zCM).mp4"}]},{"id":787,"type":"movie","title":"The Final Destination","description":"Horror ကားကြိုက်နှစ်သက်သူတို့အဖို့  ကြည့်ဖူးသမျှထဲမယ် သူတို့ရဲ့ နှလုံးသည်းအူကို လှုပ်ရမ်းနိုင်တဲ့ ဇာတ်ကားများကို ပြောပါဆိုရင်\r\nFinal Destination တွေကိုပြောကြမှာသေချာသလောက်ပါပဲ….ယ္ခုနောက်ပိုင်းထွက်တဲ့ horror ကားတော်တော်များများမှာ အထူးသဖြင့် Jump scare မျိုး ဝုန်းကနဲဒိုင်းခနဲ ခြောက်လှန့်တတ်တဲ့ ကားမျိုးတွေကို horror ကား ကြိုက်နှစ်သက်သူသူတို့အဖို့ ကြာလာတော့ အနည်းငယ်ရိုးအီလာသလိုပါပဲ…….Final Destination လို horror မျိုးကျတော့လည်း တကယ့်ကို သွေးပျက်ထိတ်လန့်စရာဖြစ်တဲ့အပြင်ကျောထဲစိမ့်နေအောင် ကြောက်နေရတာမျိုး….မင်း horror ဘယ်လောက် crazy ဖြစ်လဲဆိုတာကို Final Destination (1 to 5)ကို စဆုံးကြည့်ဖြစ်လားဆိုတာမျိုးနဲ့ ဆုံးဖြတ်ရလောက်အောင် သွေးပျက်ထိတ်လန့်စရာပါပဲ…","year":2009,"imdb":5.2,"comment":true,"rating":0,"duration":"82 min","downloadas":"1","playas":"1","classification":"850 MB","image":"https://app.zchannelmovie.com/uploads/cache/poster_thumb/uploads/jpg/f2b52d180ac1070688cef0c91239e8b6.jpg","genres":[{"id":5,"title":"Horror & Thriller"}],"sources":[{"id":4788,"type":"mp4","url":"https://f002.backblazeb2.com/file/zstorage501/movies/Final.Destination/Final.Destination.4.2009.(zCM).mp4"}]},{"id":786,"type":"movie","title":"Final Destination 3","description":"Horror ကားကြိုက်နှစ်သက်သူတို့အဖို့  ကြည့်ဖူးသမျှထဲမယ် သူတို့ရဲ့ နှလုံးသည်းအူကို လှုပ်ရမ်းနိုင်တဲ့ ဇာတ်ကားများကို ပြောပါဆိုရင်\r\nFinal Destination တွေကိုပြောကြမှာသေချာသလောက်ပါပဲ….ယ္ခုနောက်ပိုင်းထွက်တဲ့ horror ကားတော်တော်များများမှာ အထူးသဖြင့် Jump scare မျိုး ဝုန်းကနဲဒိုင်းခနဲ ခြောက်လှန့်တတ်တဲ့ ကားမျိုးတွေကို horror ကား ကြိုက်နှစ်သက်သူသူတို့အဖို့ ကြာလာတော့ အနည်းငယ်ရိုးအီလာသလိုပါပဲ…….Final Destination လို horror မျိုးကျတော့လည်း တကယ့်ကို သွေးပျက်ထိတ်လန့်စရာဖြစ်တဲ့အပြင်ကျောထဲစိမ့်နေအောင် ကြောက်နေရတာမျိုး….မင်း horror ဘယ်လောက် crazy ဖြစ်လဲဆိုတာကို Final Destination (1 to 5)ကို စဆုံးကြည့်ဖြစ်လားဆိုတာမျိုးနဲ့ ဆုံးဖြတ်ရလောက်အောင် သွေးပျက်ထိတ်လန့်စရာပါပဲ…","year":2006,"imdb":5.8,"comment":true,"rating":5,"duration":"93 min","downloadas":"1","playas":"1","classification":"863 MB","image":"https://app.zchannelmovie.com/uploads/cache/poster_thumb/uploads/jpg/3b0a46a35cbcdcaaae0bf96a3d44af87.jpg","genres":[{"id":5,"title":"Horror & Thriller"}],"trailer":{"id":4787,"type":"youtube","url":"https://youtu.be/-m_GmDZ7pSY"},"sources":[{"id":4786,"type":"mp4","url":"https://f002.backblazeb2.com/file/zstorage501/movies/Final.Destination/Final.Destination.3.2006.(zCM).mp4"}]},{"id":785,"type":"movie","title":"Fantastic Beasts and Where to Find Them","description":"ဒီဇာတ်လမ်းဟာ ဟယ်ရီပေါ်တာဇာတ်လမ်းတွေရဲ့ မှော်လောကထဲမှာ ဖြစ်ပျက်ခဲ့တဲ့အကြောင်းတွေပါပဲ။ ဒါပေမယ် ဖြစ်ပျက်နေတဲ့ကာလဟာ ၁၉၂၆ ဖြစ်ပြီး ကျောင်းအုပ်ဆရာကြီး အဲဘတ်စ် ဒန်ဘယ်လ်ဒိုးရဲ့လူငယ်ကာလဖြစ်ပါတယ်။ အဲဒီကာလရဲ့ နာမည်ကြီးမှော်နက်ဆရာကတော့ ဟယ်ရီစာအုပ်ထဲမှာ နာမည်ဖော်ပြခဲ့တဲ့ ဂရင်ဒီဝေါလ်ပါ။ ဒီဇာတ်ကားရဲ့ အဓိကဇာတ်ကောင်ကတော့ မှော်ပညာ နဲ့ မှော်သတ္တဗေဒ ပညာရှင်  နျု စကန်မန်ဒါပါ(ဟယ်ရီတို့ ကာလမှာ နျုရဲ့စာအုပ်တွေဟာ ကျောင်းအတွက် ပြဌာန်းစာအုပ်ဖြစ်လာခဲ့ပါတယ် ဟက်ဂရစ်လက်စွဲပေါ့)။ နျုဟာ လန်ဒန်ကနေ နယူးယောက်ကို မှော်သတ္တဝါဆန်းတွေ အပြည့်ပါတဲ့ လက်ဆွဲအိတ်တစ်လုံးနဲ့ ရောက်လာခဲ့ပါတယ်။ အဲဒီအချိန်မှာပဲ နယူးယောက်မှာ အဖြေရှာမရတဲ့ ထူးဆန်းတဲ့တိုက်ခိုက်မှုတွေ ပေါ်ပေါက်နေပါတယ်။ အမေရိကန်အခေါ် No-Maj (ဗြိတိန်အခေါ် မက်ဂယ်) မှော်ပညာမတတ်တဲ့ သာမာန်လူသားတစ်ဦးနဲ့ မတော်တဆအလွဲတွေ ဖြစ်ရင်း သူ့ရဲ့သေတ္တာထဲကနေ သတ္တဝါအချို့လွတ်မြောက်သွားတဲ့အခါ တိုက်ခိုက်မှုတွေရဲ့အကြောင်းရင်းဟာ သူ့ကြောင့်လို့ သံသယဖြစ်စရာတွေပေါ်လာပြီး ဖြေရှင်းဖို့ကြိုးစားရပါတော့တယ်။ ဒီဇာတ်ကားဟာ ၅ ကားအထိ ဆက်ရိုက်ဖို့ သတင်းထုတ်ပြန်ထားတာမို့ ဒီကားလေးကြည့်ပြီးရင် နောက်နှစ်တွေအတွက် ဆက်ပြီး စောင့်မျှော်ကြတာပေါ့ဗျာ။","year":2016,"imdb":7.3,"comment":true,"rating":0,"duration":"132 min","downloadas":"1","playas":"1","classification":"952 MB","image":"https://app.zchannelmovie.com/uploads/cache/poster_thumb/uploads/jpg/64040fc17aeb781329febda46e0e012f.jpg","genres":[{"id":7,"title":"Fantasy"}],"trailer":{"id":4785,"type":"youtube","url":"https://youtu.be/YdgQj7xcDJo"},"sources":[{"id":4784,"type":"mp4","url":"https://f002.backblazeb2.com/file/zstorage501/movies/2016/Fantastic.Beasts.And.Where.To.Find.Them..2016..(MM.Sub).mp4"}]},{"id":783,"type":"movie","title":"The Godfather: Part III","description":"Part III လာပါပြီ …ထုံးစံအတိုင်းပေါ့ဗျာ… ဒီကားရဲ့အညွှန်းကိုတော့ မရေးရဲလို့မရေးတော့ဘူး…ကိုင်းခံစားကြည့်လိုက်ပါဦးဗျို့…","year":1990,"imdb":7.6,"comment":true,"rating":5,"duration":"162 min","downloadas":"1","playas":"1","classification":"1.55 GB","image":"https://app.zchannelmovie.com/uploads/cache/poster_thumb/uploads/jpg/4cbc78c22c71832e8bcaaaf02a707e0a.jpg","genres":[{"id":6,"title":"Crime"}],"trailer":{"id":4779,"type":"youtube","url":"https://youtu.be/z8h3LVb8cl8"},"sources":[{"id":4778,"type":"mp4","url":"https://f002.backblazeb2.com/file/zstorage501/movies/The.Godfather/The.Godfather.3..1990..(MM.Sub).mp4"}]},{"id":782,"type":"movie","title":"The Godfather: Part II","description":"Part 2 လာပါပြီ …ထုံးစံအတိုင်းပေါ့ဗျာ… ဒီကားရဲ့အညွှန်းကိုတော့ မရေးရဲလို့မရေးတော့ဘူး…\r\nတစ်ခုတော့ပြောလို့ရတယ်…ခင်ဗျားတို့ရဲ့ ရုပ်ရှင်ကြည့်သမိုင်းမှာ ထာဝရအကောင်းဆုံးဆိုသော ဇာတ်ကားစာရင်းထဲမှာ အခုရော နောင်ရောအမြဲရှိနေလိမ့်မယ်လို့ပါ…ကိုင်းခံစားကြည့်လိုက်ပါဦးဗျို့…1080p တော့မတင်တော့ဘူးစဉ်းစားထားတယ်…720p ကို အကောင်းမွန်ဆုံးတင်ပေးထားပါတယ်..","year":1974,"imdb":9,"comment":true,"rating":0,"duration":"202 min","downloadas":"1","playas":"1","classification":"1.84 GB","image":"https://app.zchannelmovie.com/uploads/cache/poster_thumb/uploads/jpg/7e6d6813ea4de117a8277edd9809aff6.jpg","genres":[{"id":6,"title":"Crime"}],"trailer":{"id":4777,"type":"youtube","url":"https://youtu.be/9O1Iy9od7-A"},"sources":[{"id":4776,"type":"mp4","url":"https://f002.backblazeb2.com/file/zstorage501/movies/The.Godfather/The.Godfather.2..1974..(MM.Sub).mp4"}]},{"id":781,"type":"movie","title":"The Godfather","description":"ဒီကားရဲ့ ကောင်းမွန်ခြင်းတွေ အောင်မြင်မှုတွေကို တော်တော်များများသိကြမယ်ထင်ပါတယ်…..အော်စကာ (၃)ဆုရထားသလို အကောင်းမွန်ဆုံးသော Rating ရ ကာစာရင်းထဲမှာ အမြဲတမ်းရှိနေလေရဲ့….ဒီကားရဲ့ အညွှန်းကိုလည်း မရေးတာက ကြည့်တဲ့သူအတွက်ပိုကောင်းပါတယ်…တစ်ခုပြောချင်တာက မကြည့်ရသေးတဲ့သူတွေအဖို့ရှေ့ပိုင်းမိနစ်(၃၀)လောက်ကို စိတ်ရှည်ပေးပါ…ဇာတ်လမ်းရဲ့ အဓိက ဇာတ်ကောင်တွေ စရိုက်တွေအပြုအမူတွေကို တဖြည်းဖြည်းချပြရင်း တကယ့်အကောင်းအမွန်ဆုံးသောအပိုင်းတွေကို ဆွဲခေါ်သွားမှာပို့ပါ…ကိုင်း ရုပ်ရှင်ချစ်ပရိတ်သတ်ကြီးများ ပြန်လည်ခံစားကြည့်လိုက်ပါဦး","year":1972,"imdb":9.2,"comment":true,"rating":0,"duration":"175 min","downloadas":"1","playas":"1","classification":"1.05 GB","image":"https://app.zchannelmovie.com/uploads/cache/poster_thumb/uploads/jpg/d984422d7af1f8788b6eed5ac04ab29d.jpg","genres":[{"id":6,"title":"Crime"}],"trailer":{"id":4775,"type":"youtube","url":"https://youtu.be/fBNpSRtfIUA"},"sources":[{"id":4774,"type":"mp4","url":"https://f002.backblazeb2.com/file/zstorage501/movies/The.Godfather/THE.GODFATHER.1972.720NEWP.mp4"}]},{"id":779,"type":"movie","title":"Home Alone: The Holiday Heist","description":"ကျန်တော်တို့ ငယ်ငယ်တုန်းက အရမ်းကြိုက်ပြီး \r\nတဟားဟားရီခဲ့ရတဲ့ ကလေးဟာသကားလေးပါ......\r\nအားလုံး သိပြီးသားမို့ Review ရှည်လို့ မရေးတော့ပါဘူး.....\r\n\r\nပြန်ကြည့်ချင်သူတွေအတွက် တင်ပေးလိုက်ပါတယ်.....","year":2012,"imdb":3.5,"comment":true,"rating":0,"duration":"87 min","downloadas":"1","playas":"1","classification":"0.98 GB","image":"https://app.zchannelmovie.com/uploads/cache/poster_thumb/uploads/jpg/64ad3a41772def9f88726e96a81889bf.jpg","genres":[{"id":9,"title":"Comedy"}],"trailer":{"id":4763,"type":"youtube","url":"https://youtu.be/EvJy9gROP4U"},"sources":[{"id":4762,"type":"mp4","url":"https://f002.backblazeb2.com/file/zstorage501/movies/Home.Alone/Home.Alone.5.-.The.Holiday.Heist.(2012).HDTV.720p.mp4"}]},{"id":778,"type":"movie","title":"Home Alone 4: Taking Back the House","description":"ကျန်တော်တို့ ငယ်ငယ်တုန်းက အရမ်းကြိုက်ပြီး \r\nတဟားဟားရီခဲ့ရတဲ့ ကလေးဟာသကားလေးပါ......\r\nအားလုံး သိပြီးသားမို့ Review ရှည်လို့ မရေးတော့ပါဘူး.....\r\n\r\nပြန်ကြည့်ချင်သူတွေအတွက် တင်ပေးလိုက်ပါတယ်.....","year":2002,"imdb":2.6,"comment":true,"rating":0,"duration":"89 min","downloadas":"1","playas":"1","classification":"902 MB","image":"https://app.zchannelmovie.com/uploads/cache/poster_thumb/uploads/jpg/cfb277d371e21b852fac9d2a95bd97f0.jpg","genres":[{"id":9,"title":"Comedy"}],"trailer":{"id":4761,"type":"youtube","url":"https://youtu.be/Pviq6Tw5sNA"},"sources":[{"id":4760,"type":"mp4","url":"https://f002.backblazeb2.com/file/zstorage501/movies/Home.Alone/Home.Alone.4.-.Taking.Back.The.House.(2002).Blu-Ray.1080p.5.1CH.mp4"}]},{"id":777,"type":"movie","title":"Home Alone 3","description":"ကျန်တော်တို့ ငယ်ငယ်တုန်းက အရမ်းကြိုက်ပြီး \r\nတဟားဟားရီခဲ့ရတဲ့ ကလေးဟာသကားလေးပါ......\r\nအားလုံး သိပြီးသားမို့ Review ရှည်လို့ မရေးတော့ပါဘူး.....\r\n\r\nပြန်ကြည့်ချင်သူတွေအတွက် တင်ပေးလိုက်ပါတယ်.....","year":1997,"imdb":4.5,"comment":true,"rating":5,"duration":"102 min","downloadas":"1","playas":"1","classification":"0.98 GB","image":"https://app.zchannelmovie.com/uploads/cache/poster_thumb/uploads/jpg/1eda5658a876abe9391a2978735e769b.jpg","genres":[{"id":9,"title":"Comedy"}],"trailer":{"id":4759,"type":"youtube","url":"https://youtu.be/PP--dDh4axI"},"sources":[{"id":4758,"type":"mp4","url":"https://f002.backblazeb2.com/file/zstorage501/movies/Home.Alone/Home.Alone.3.(1997).Web-DL.1080p.mp4"}]},{"id":776,"type":"movie","title":"Home Alone 2: Lost in New York","description":"ကျန်တော်တို့ ငယ်ငယ်တုန်းက အရမ်းကြိုက်ပြီး \r\nတဟားဟားရီခဲ့ရတဲ့ ကလေးဟာသကားလေးပါ......\r\nအားလုံး သိပြီးသားမို့ Review ရှည်လို့ မရေးတော့ပါဘူး.....\r\n\r\nပြန်ကြည့်ချင်သူတွေအတွက် တင်ပေးလိုက်ပါတယ်.....","year":1992,"imdb":6.7,"comment":true,"rating":0,"duration":"120 min","downloadas":"1","playas":"1","classification":"1.13 GB","image":"https://app.zchannelmovie.com/uploads/cache/poster_thumb/uploads/jpg/13120118c36766031a2dc193f08f1e46.jpg","genres":[{"id":9,"title":"Comedy"}],"trailer":{"id":4757,"type":"youtube","url":"https://youtu.be/k0kJieJ1k6k"},"sources":[{"id":4756,"type":"mp4","url":"https://f002.backblazeb2.com/file/zstorage501/movies/Home.Alone/Home.Alone.2.-.Lost.in.New.York.(1992).Blu-Ray.1080p.mp4"}]},{"id":775,"type":"movie","title":"Home Alone","description":"ကျန်တော်တို့ ငယ်ငယ်တုန်းက အရမ်းကြိုက်ပြီး \r\nတဟားဟားရီခဲ့ရတဲ့ ကလေးဟာသကားလေးပါ......\r\nအားလုံး သိပြီးသားမို့ Review ရှည်လို့ မရေးတော့ပါဘူး.....\r\n\r\nပြန်ကြည့်ချင်သူတွေအတွက် တင်ပေးလိုက်ပါတယ်.....","year":1990,"imdb":7.6,"comment":true,"rating":0,"duration":"103 min","downloadas":"1","playas":"1","classification":"1.07 GB","image":"https://app.zchannelmovie.com/uploads/cache/poster_thumb/uploads/jpg/e3986c4e2041be6dd1dae6a31a46a639.jpg","genres":[{"id":9,"title":"Comedy"}],"trailer":{"id":4755,"type":"youtube","url":"https://youtu.be/0iNmVVlmmv8"},"sources":[{"id":4754,"type":"mp4","url":"https://f002.backblazeb2.com/file/zstorage501/movies/Home.Alone/Home.Alone.(1990).Blu-Ray.1080p.mp4"}]},{"id":773,"type":"movie","title":"Pacific Rim: Uprising","description":"Pacific Rim ရဲ့ ဒုတိယမြောက်ကားလေး ၅နှစ်ကြာတဲ့အခါ ပရိသတ်ရှေ့ ရောက်လာပါပြီ။IMDb Ratinf 6/10 ရထားပြီးတော့ ဘတ်ဂျပ် $ ၁၇၀millionကျော်အကုန်အကျခံပြီး ရိုက်ကူးတင်ဆက်ထားတာပါ။\r\nဇာတ်လမ်းအကျဉ်းလေးကတော့ Pacifim Rim တုန်းက ကိုင်ဂျူးလို့ခေါ်တဲ့ဂြိုလ်သားတွေရဲ့ ကျူးကျော်မှုကိုတိုက်ခိုက်မှုကို ယေဂါလို့ခေါ်တဲ့ ဧရာမစက်ရုပ်ကြီးတွေနဲ့\r\nတန်ပြန်တိုက်ခိုက် လို့အောင်မြင်ခဲ့ပြီး ကမ္ဘာနှစ်ခုဆက်သွယ်ထားတဲ့ တွင်းပေါက်ကြီးကိုဖျက်ဆီးပစ်နိုင်ခဲ့တာ ၁၀ နှစ်ကျော်ကာလကို ရောက်ရှိနေပါပြီ။ဒါပေမယ့် ယေဂါတွေရဲ့ အားနည်းချက်ကတော့ စက်ရုပ်ရဲ့ တိုက်ခိုက်နိုင်စွမ်းဟာသူ့ကိုမောင်းနှင်တဲ့ ပိုင်းလော့ဒ်နှစ်ယောက်ရဲ့ သဟဇာတဖြစ်မှု ပိုင်းလော့ဒ်တွေရဲ့ကျွမ်းကျင်မှုအပေါ်မူတည်နေသလို ကျူးကျော်လာတဲ့ကိုင်ဂျူးဆီကို သွားတိုက်တဲ့အခါမှာစက်ရုပ်အကြီးကြီးမို့ သယ်ယူပို့ဆောင်ရေးမှာ ကြံ့ကြာနေတဲ့အချက်ပါပဲ။ဒါကြောင့် ပိုင်းလော့ဒ်ကောင်းတွေရအောင် ငယ်စဉ်ကတည်းက လေ့ကျင့်ပေးရပါတယ်။ဒါကြောင့် လူသားတွေအနေနဲ့ ဒါတွေကို ဖြေရှင်းနိုင်ဖို့နည်းလမ်းတွေ ကြံစည်လာပါတယ်။ဒီမှာ တရုတ်နိုင်ငံ “ရှောင်-စက်မှုလုပ်ငန်း” ကနေ နည်းပညာအသစ်တွေနဲ့ ရှာကြံပြီးလူတစ်ယောက်တည်းကသာ မောင်းနှင်နိုင်ပြီး အဝေးထိန်းနဲ့ ထိန်းချုပ်နိုင်တဲ့ယေဂါဒရုန်းစက်ရုပ်ကြီးတွေကို ပိုင်းလော့ဒ်တွေရှာရတဲ့ဒုက္ခ ကိုင်ဂျူးတွေနဲ့ တိုက်ခိုက်ရင်းပိုင်းလော့ဒ်တွေမသေအောင်ဆိုပြီး တီထွင်နိုင်လိုက်ပြီး တစ်ကမ္ဘာလုံးအနှံ့တပ်ဖြန့်ထားနိုင်အောင် လုပ်ဆောင်နေပါပြီ…….-ဒီလိုအဖက်ဖက် အဆင်သင့်ပြင်ထားပေမယ့် ကိုင်ဂျူးတွေဖက်ကရောကျူးကျော်ဖို့ ဘာတွေဘယ်လိုပြင်ဆင်နေကြသလဲ-ကိုင်ဂျူးတွေအရင်က အကောင်သေးတွေကနေ တဖြည်းဖြည်း ဆင့်ကဲတိုးတက်လာလို့အရင်က အဆင့်-၄ အဆင့်-၅ လောက်ရှိတဲ့အကောင်ကြီးတွေကအခုရောဘယ်အဆင့်ထိ သတ်မှတ်နိုင်တဲ့ ကိုင်ဂျူးအကောင်ကြီးမျိုးတွေဖြစ်လာမှာလဲ-ဒီကားထဲမှာ ယေဂါတွေထဲက နာမည်ကျော်စက်ရုပ်တွေဖြစ်တဲ့ဂျစ်ပစီအဗန်းဂျား…နိုဝင်ဘာအေဂျက်….ဆေဗာအသီနာ…..ဂါးဒီးယမ်းဘရာဗို….ဘရေဇာဖီးနစ်အစရှိတဲ့ဧရာမစက်ရုပ်ကြီးတွေက ဘယ်လိုအစွမ်းအစရှိသလဲတာကို ကြည့်လိုက်ကြရအောင်…..","year":2018,"imdb":5.6,"comment":true,"rating":3.3,"duration":"111 min","downloadas":"1","playas":"1","classification":"793 MB","image":"https://app.zchannelmovie.com/uploads/cache/poster_thumb/uploads/jpg/c5252248b0ba0e12648e9ba151b884f3.jpg","cover":"https://app.zchannelmovie.com/uploads/cache/cover_thumb/uploads/jpg/e1a570624d9b608e35ec6b76c375fcf3.jpg","genres":[{"id":8,"title":"Sci-Fi"}],"trailer":{"id":4713,"type":"youtube","url":"https://youtu.be/fUjicxMPDzs"},"sources":[{"id":4712,"type":"mp4","url":"https://f002.backblazeb2.com/file/zstorage501/movies/2018/Pacific.Rim.II(2018).mp4"}]},{"id":772,"type":"movie","title":"Dhoom 3","description":"ဇာတ်လမ်းအကျဉ်းကတော့…\r\n၁၉၉၀ ပြည့်နှစ်ကာလမှာ အိန္ဒိယလူမျိုး မျက်လှည့်ဆရာ Iqbal Haroon Khan ဟာ သူ့ရဲ့ ဆပ်ကပ်အဖွဲ့ မပြိုကွဲရေးအတွက် ရုန်းကန်နေရပါတယ်။ ဒီဆပ်ကပ် ဆက်လက်ရပ်တည်ဖို့အတွက် အနောက်ချီကာဂိုဘဏ်ကို မှီခိုနေရပါတယ်။ ဒါပေမယ့် ဘဏ်ပိုင်ရှင် Anderson ကတော့ ဒီဆပ်ကပ်ကို ပိတ်ပစ်ဖို့ပဲ ဖိအားပေးနေပါတယ်။ အထူးဖျော်ဖြေပွဲအဖြစ် Khan ဟာ Anderson ကို သူ့ရဲ့ အကောင်းဆုံး ပြကွက်တစ်ခုကို ပြသပြီး ဆပ်ကပ်အဖွဲ့ မဖျက်သိမ်းရဖို့ ကြိုးစားပါတယ်။ ဒါပေမယ့် ဒီဆပ်ကပ်အဖွဲ့ကို ပိတ်ပစ်ဖို့ပဲ တမင်လုပ်နေတဲ့ Anderson ဟာ ဘာကိုမှ အရေးမလုပ်တာမို့ Khan ဟာ ကိုယ့်ကိုယ်ကို သတ်သေသွားပါတယ်။ အဲဒီအဖြစ်အပျက်ကို ဖခင်နဲ့အတူ ဆပ်ကပ်ပြပြီး Anderson ဆီက အကူအညီ မျှော်လင့်နေရှာတဲ့ Sahir Khan ဟာ အစအဆုံး မြင်တွေ့လိုက်ရပါတယ်။\r\nSahir Khan ဟာ လက်ရှိအချိန်မှာတော့ Great Indian Circus ကို ပြန်လည်ထူထောင် လည်ပတ်နေပါတယ်။ ဒီတစ်ခါ ကပြမယ့် ဆပ်ကပ်ပြပွဲအတွက် နတ်သမီးတစ်ပါးလို ကပြဖျော်ဖြေနိုင်မယ့် အကမယ်တစ်ဦး လိုအပ်နေပါတယ်။ အဲဒီအကမယ်အဖြစ် အရမ်းသွက်လက်တဲ့ မိန်းကလေးတစ်ယာက်ကို သူရှာဖွေတွေ့ရှိသွားပါတယ်။ တစ်ဖက်ကလည်း အနောက်ချီကာဂိုဘဏ်ကို ဖြိုခွဲနိုင်ဖို့ ကြိုးစားနေပါတယ်။ ဒါပေမယ့် သူကြိုးစားနေတာ ဥပဒေဘောင်ထဲကတော့ မဟုတ်ပါဘူး။ ဘဏ်ခွဲတွေကို ဖောက်ထွင်းပြီး မျက်လှည့်ဆန်ဆန် ပြကွက်တွေနဲ့ လွတ်အောင် ထွက်ပြေးရင်း လိုက်တမ်းပြေးတမ်း ကစားနေတာပါ။ သူ့ဖောက်ထွင်းပြီးတိုင်း သူတို့မိသားစုရဲ့ လက်ကိုင်ဆောင်ပုဒ်ကို ဟင်ဒီဘာသာနဲ့ ရေးထားခဲ့ပါတယ်။ ဒါကြောင့် ချီကာဂို ရဲတပ်ဖွဲ့ဟာ အိန္ဒိယနိုင်ငံက နာမည်ကျော် ရဲမှူး Jai Dixit နဲ့ သူ့ပါတနာ Ali ကို အကူအညီ တောင်းပါတယ်။ Jai Dixit ဟာ ချီကာဂို ရဲတပ်ဖွဲ့က ရဲမှူး Victoria နဲ့ သိကျွမ်းသူဖြစ်တာကြောင့် စုံစမ်းစစ်ဆေးရေးကို အခက်အခဲမရှိ ဆောင်ရွက်နိုင်ပေမယ့် တရားခံကတော့ စုံးစုံးမြုပ်နေပါတယ်။\r\nဒါကြောင့် Jai ဟာ တရားခံရဲ့ စိတ်ကို ဆွတဲ့အနေနဲ့ ရုပ်မြင်သံကြားကနေ တရားခံကို နှိမ့်ချဝေဖန်လိုက်ပါတယ်။ မခံချင်ဖြစ်သွားတဲ့ Sahir ဟာ Jai မျက်စိရှေ့တင်ပဲ နောက်ထပ် ဘဏ်ခွဲတစ်ခုကို ထပ်မံ ဖောက်ထွင်းပြလိုက်ပါတယ်။ ဒါပေမယ့် ကံမကောင်းချင်တော့ Jai က Sahir ရဲ့ လက်ပြင်ကို သေနတ်နဲ့ ပစ်နိုင်ခဲ့ပါတယ်။ ဒီဒဏ်ရာနဲ့ Sahir ကို Jai က သူ့ရဲ့ မျက်လှည့်ပွဲမှာ ဝင်ဖမ်းတဲ့အခါ Sahir မှာ သေနတ်ဒဏ်ရာ လုံးဝမရှိတာကို တွေ့ရပါတယ်။ Sahir ရဲ့ အဆိုအရ သူ့အဖေ Khan ဟာ အကောင်းဆုံး လျှို့ဝှက်ချက်တစ်ခုနဲ့ ကမ္ဘာကြီးကို အံ့ဖွယ်ပြကွက် ပြသနိုင်ဖို့ ရည်ရွယ်ထားခဲ့တာပါ။ သူ့အဖေဆီက သူဆက်ခံခဲ့တဲ့ လျှို့ဝှက်ချက်ဆိုတာ ဘာဖြစ်မလဲ ….\r\nAamir Khan က မျက်လှည့်ဆရာ Sahir အဖြစ် ပါဝင်သရုပ်ဆောင်ထားပြီး အကမယ် Aaliya အဖြစ် Katrina Kaif က ပါဝင်သရုပ်ဆောင်ထားတယ့် Dhoom 3 ဟာ အရင် Dhoom ဇာတ်ကားတွေထက် ရိုက်ချက်တွေ ပိုမိုအသားပေး ရိုက်ကူးထားပြီး အလှအပနဲ့ အကခန်းတွေ၊ အတိုက်အခိုက်ခန်းတွေမှာ အကောင်းဆုံးဖြစ်အောင် ဖန်တီးထားတာ တွေ့ရပါတယ်။ Katrina Kaif ရဲ့ လှပတဲ့ ကကွက်တွေကို အတော်လေး အသေးစိတ် ရိုက်ကူးထားသလို ဆိုင်ကယ်စတန့်ပြကွက် မြောက်များစွာကို သေသေချာချာ ရိုက်ကူးတင်ဆက်ထားတာ တွေ့ရပါတယ်။ မထင်မှတ်တဲ့ ဇာတ်အိမ်၊ အကောင်းဆုံးရိုက်ချက်၊ အလှပဆုံးပြကွက်တွေနဲ့ ဖန်တီးထားပေမယ့် အိန္ဒိယသားတွေကို အသားပေးပြီး ချီကာဂိုရဲတွေရဲ့ ကဏ္ဍကို လျှော့ချလိုက်တဲ့အခါမှာ အလွန်အကျွံ ဖြစ်သွားတာလေး နည်းနည်းတော့ ရှိပါတယ်။ အရင်ဇာတ်ကားတွေထက် ဇာတ်လမ်းပိုင်း အားနည်းပြီး Sahir ရဲ့ ဇာတ်အိမ်က ပိုများနေတာကြောင့် Jai ရဲ့ စုံစမ်းထောက်လှမ်းမှုကို ချုံ့လိုက်ရသလိုဖြစ်ပြီး ဇာတ်အိမ်က လေးသွားပါတယ်။\r\nJai Dixit အဖြစ် Abhishek Bachchan နဲ့ Ali အဖြစ် Uday Chopra တို့ ဆက်လက်ပါဝင်သရုပ်ဆောင်ထားပြီး IMDB မှာ Rating 6.4 ရရှိထားပါတယ်။ Rotten Tomatoes မှာလည်း Tomatometer 86% ရရှိထားပြီး Dhoom ဇာတ်ကားတွေရဲ့ ထုံးစံအတိုင်း အလှအပနဲ့ အကြမ်းပတမ်းကို အကောင်းမွန်ဆုံး ပေါင်းစပ်ထားတာကို တွေ့ရမှာပါ။ ဇာတ်လမ်းအဆုံးမှာ ပုံမှန်ပါလေ့ရှိတဲ့ Dhoom သီချင်းကို Katrina Kaif ရဲ့ အကအလှနဲ့ တွဲဖက်ပြီး ခံစားကြည့်ရှုကြပါဦး","year":2013,"imdb":5.4,"comment":true,"rating":3.1,"duration":"172 min","downloadas":"1","playas":"1","classification":"1.35 GB","image":"https://app.zchannelmovie.com/uploads/cache/poster_thumb/uploads/jpg/7c00499975d7d56e8c1228054b064285.jpg","genres":[{"id":1,"title":"Action"},{"id":12,"title":"Bollywood (India)"}],"sources":[{"id":4711,"type":"mp4","url":"https://f002.backblazeb2.com/file/zstorage501/movies/2013/Dhoom-3-2013.720p.mp4.mp4"}]},{"id":771,"type":"movie","title":"Dhoom 2","description":"မကြည့်ဖူးတဲ့သူမရှိလောက်အောင်နာမည်ကြီးခဲ့တဲ့ဘောလိဝုဒ်ဇာတ်ကားတစ်ကားပါ။လက်ပွားမင်းသားရဲ့အကောင်းဆုံးဇာတ်ကားတစ်ကားလို့လည်းပြောလို့ရပါတယ်။ဒီဇာတ်ကားထဲမှာတော့ လက်ပွားမင်းသားဟာ Professional သူခိုးတစ်ယောက်ရဲ့ကာရိုက်တာကိုပီပြင်စွာသရုပ်ဆောင်ထားတာကိုတွေ့ရမှာဖြစ်ပါတယ်။ Dhoomကားရဲ့အဓိကဇာတ်ကောင်တွေဖြစ်တဲ့ ACP Jay Dixit နဲ့ Ali တို့ရဲ့နေရာကို Abishek Bachan နဲ့ Uday chopraတို့ကသရုပ်ဆောင်ထားပါတယ်။မယ်ကမ္ဘာဆုရထားတဲ့မင်းသမီးချော Aishwarya Rai ကလည်း နှစ်ဖက်ချွန်တစ်ယောက်အဖြစ်သရုပ်ဆောင်ထားပါတယ်။ ဒီဇာတ်ကားတစ်ခုလုံးကို ထိန်းသွားတာကတော့ လက်ပွားမင်းသား Hrithik Roshanပါပဲ။ Aryanရဲ့ဇာတ်ကောင်နေရာကနေ ရုပ်ပြောင်းရုပ်လွှဲတွေကိုတစ်ဝကြီးကြည့်ရှုခံစားရမှာပါ။အယောက်၁၀၀မှာ၉၀လောက်ကြည့်ပြီးသားဖြစ်တဲ့ဇာတ်ကားလေးမို့ review ကိုအတိုချုံ့ပဲရေးပေးလိုက်ပါတယ်","year":2006,"imdb":6.5,"comment":true,"rating":3.5,"duration":"152 min","downloadas":"1","playas":"1","classification":"608 MB","image":"https://app.zchannelmovie.com/uploads/cache/poster_thumb/uploads/jpg/8c8a98e2f23e33a62200231480bb4aba.jpg","genres":[{"id":1,"title":"Action"},{"id":12,"title":"Bollywood (India)"}],"sources":[{"id":4710,"type":"mp4","url":"https://f002.backblazeb2.com/file/zstorage501/movies/2006/Dhoom-2-2006_360p.mp4"}]},{"id":770,"type":"movie","title":"Dhoom","description":"Dhoom ကားတွေရဲ့ပထမဆုံးကားလေးပါ။ ဆိုင်ကယ်တွေနဲ့အုပ်စုလိုက် ဓါးပြတိုက်နေတဲ့ ဓါးပြအဖွဲ့တစ်ဖွဲ့ကို လိုက်လံဖမ်းစီးပုံကို ရိုက်ပြထားတာပါ။ ဒီဇာတ်ကားလေးထဲမှာ ACP Jay Dixit နဲ့ Ali တို့ဘယ်လိုစတွေ့ခဲ့တယ်ဆိုတာပါသိရမှာဖြစ်ပါတယ်။အမြဲချိန်ပါဖြစ်နေတဲ့ Ali ရဲ့ဘဝကို သနားစဖွယ်တွေ့ရမှာဖြစ်ပါတယ်။ ဒီဇာတ်ကားထဲမှာပါတဲ့ဓါးပြအဖွဲ့ရဲ့ခေါင်းဆောင်ကတော့ အခု အိန္ဒိယမှာ ပျိုတိုင်းကြိုက်တဲ့နှင်းဆီခိုင်ဖြစ်နေတဲ့ မင်းသား john abraham ဖြစ်ပါတယ်။ Dhoom 2 နဲ့ 3လောက်မကောင်းပေမယ့်လည်း ယှဉ်ကြည့်လို့ရတဲ့ကားလေးတစ်ကားပါ။","year":2004,"imdb":6.7,"comment":true,"rating":0,"duration":"129 min","downloadas":"1","playas":"1","classification":"0.99 GB","image":"https://app.zchannelmovie.com/uploads/cache/poster_thumb/uploads/jpg/bbb0f018f91f00c013d647b2bf39e317.jpg","genres":[{"id":1,"title":"Action"},{"id":12,"title":"Bollywood (India)"}],"sources":[{"id":4709,"type":"mp4","url":"https://f002.backblazeb2.com/file/zstorage501/movies/2004/Dhoom.2004.large.mp4"}]},{"id":769,"type":"movie","title":"Rampage","description":"အမေရိကန် အထူးတပ်ဖွဲ့ ဝင်ဟောင်းတစ်ဦးဖြစ်တဲ့ ဒေးဗစ်အိုကွေဟာ ဆန်ဒီရေးဂိုးတောရိုင်း တိရစ္ဆာန် ကာကွယ်စောင့်ရှောက် ရေးဌာနက ဂေါ်ရီလာမျောက်ဝံ တွေနဲ့ပတ်သက်ပြီး သုတေသန ပြုနေတဲ့ နာမည်ကြီး ပညာရှင် တစ်ယောက်ပါ။မုဆိုးတွေလက်ကနေ ကယ် ဆယ်လာခဲ့တဲ့ ဂျော့ချ်ဆိုတဲ့ ဂေါ်ရီ လာမျောက်ဝံဖြူကြီးဟာ သာမန် မျောက်ဝံတွေနဲ့မတူဘဲ ထူးခြားတဲ့ အသိဉာဏ်ဖွံ့ဖြိုးမှုမျိုးရှိနေတယ်ဆိုတာ ဒေးဗစ်က သတိထားမိပြီး ဂျော့ချ်နဲ့လည်း ရင်းနှီးခဲ့ပါတယ်။တစ်ရက်မှာတော့ ဂျော့ချ် နေတဲ့နေရာကို ထူးဆန်းတဲ့ ပစ္စည်းတစ်ခုကျလာပြီး အဲဒါကို ဂျော့ချ် က ထိလိုက်တဲ့အခါမှာတော့ ည တွင်းချင်းမှာကို ဂျော့ချ်စိတ်ရိုင်း ဝင်ကာ ခန္ဓာကိုယ်အရွယ်အစား ကလည်း အကြီးကြီးဖြစ်သွားခဲ့ပါ တယ်။အဲဒီနောက်မှာတော့ ဒေးဗစ် ကို မျိုးရိုးဗီဇဆိုင်ရာ ပညာရှင် ဒေါက်တာကိတ်ကဲလ်ဝဲက ဆက် သွယ်ပြီး ဂျော့ချ် အခုလိုဖြစ်သွား တာဟာ Energyne ကုမ္ပဏီက စမ်းသပ်ထားတဲ့ သန္ဓေပြောင်း ပစ္စည်းကြောင့်လို့ပြောပါတယ်။ဒေါက်တာကိတ်ကိုလည်း Energyne ကုမ္ပဏီက အလုပ် ထုတ်ပစ်ခဲ့သလို ကုမ္ပဏီနဲ့ စမ်း သပ်မှုတွေကို ထုတ်ပြောလို့ဆိုပြီး ထောင်ချပစ်ဖို့အထိပါ လုပ်ခဲ့ပါ တယ်။\r\nဂျော့ချ်ကို အေးဂျင့်ဟာဗေး ရက်ဆဲလ်ဦးဆောင်တဲ့ အစိုးရ အဖွဲ့အစည်းက လေယာဉ်နဲ့ ဖမ်း ဆီးခေါ်ဆောင်သွားပေမယ့် လေယာဉ်ကို ဖျက်ဆီးပြီး ဂျော့ချ်လွတ် မြောက်သွားသလို ရက်ဖ်ဆိုတဲ့ သန္ဓေပြောင်း ဝံပုလွေကြီးက လည်း သူ့ကိုလိုက်ဖမ်းတဲ့အဖွဲ့ကို အပြတ်ရှင်းပစ်ခဲ့ပါတယ်။အဲဒီနောက် ဂျော့ချ်နဲ့ ရက်ဖ် တို့ ပေါင်းမိပြီး ချီကာဂိုမြို့တော် ကို ဝင်ရောက်ဖျက်ဆီး တိုက်ခိုက် ခဲ့ပါတော့တယ်။ ပြဿနာက အဲဒီ မှာတင် မပြီးသေးပါဘူး။ ကုန်းပေါ်မှာ ဂျော့ချ်နဲ့ ရက်ဖ်တို့ တိုက် ခိုက်ဖျက်ဆီးနေသလို လစ်ဇီဆို တဲ့ သန္ဓေပြောင်း မိကျောင်းကြီး ရန်ကလည်း ထပ်ပေါ်လာပါတော့ တယ်။ဒေးဗစ်နဲ့ ဒေါက်တာကိတ် ဟာ စိတ်ရိုင်းဝင်ပြီး တွေ့သမျှ အန္တရာယ်ပြုနေတဲ့ သန္ဓေပြောင်း သတ္တဝါတွေကို ပုံမှန်အခြေအနေ ပြန်ဖြစ်အောင် လုပ်နိုင်မယ်လို့ ယုံကြည်ထားကာ ထိန်းချုပ်နိုင်ဖို့ အသည်းအသန် ကြိုးပမ်းခဲ့ကြပါ တယ်။သန္ဓေပြောင်း သတ္တဝါတွေ က ဘယ်လိုတွေ ဒုက္ခပေးမှာလဲ၊ ဒေးဗစ်တို့ ယုံကြည်ထားသလို ဂျော့ချ်ကို မူလအနေအထားဖြစ် အောင် ပြန်လုပ်နိုင်ပါ့မလားဆို တာကို အမိုက်စား အထူးပြုလုပ် ချက်တွေ၊ အက်ရှင်ပြကွက်တွေနဲ့ ရိုက်ကူးထားတာမို့ ပရိသတ်တွေ သဘောကျမှာပါ။ပရိသတ်အချစ်တော် အက် ရှင်မင်းသားကြီး ဒဝိန်းဂျွန်ဆင်က အဓိက သရုပ်ဆောင်ထားတာဖြစ် ပြီး နာအိုမီဟားရစ္စ၊ မာလင်အ ကာမန်၊ ဂျက်ဖရီးဒင်းန်မော်ဂန်၊ ဂျိတ်ခ်လေစီ၊ ဂျိုးမန်ဂါနီလို စသူ တွေပါဝင်ထားပါတယ်။","year":2018,"imdb":6.1,"comment":true,"rating":3.8,"duration":"107 min","downloadas":"1","playas":"1","classification":"849 MB","image":"https://app.zchannelmovie.com/uploads/cache/poster_thumb/uploads/jpg/8ac175a94010b977990f190de6d5550e.jpg","cover":"https://app.zchannelmovie.com/uploads/cache/cover_thumb/uploads/jpg/d8838a12c192e1fcdaa506c3c780aeb5.jpg","genres":[{"id":2,"title":"Adventure"}],"trailer":{"id":4707,"type":"youtube","url":"https://youtu.be/coOKvrsmQiI"},"sources":[{"id":4706,"type":"mp4","url":"https://f002.backblazeb2.com/file/zstorage501/movies/2018/Rampage..2018..(MM.Sub).mp4"}]},{"id":768,"type":"movie","title":"47 Ronin","description":"#ရုပ်ရှင်မိတ်ဆက်ဒီကားကတော့ တစ်ချိန်က နာမည်ကြီးမင်းသား Keanu Reeves ပါဝင်သရုပ်ဆောင်ထားပြီး ဂျပန် ရဲ့ သမိုင်းဝင် သူရဲကောင်း ၄၇ ယောက်ရဲ့ တကယ့်အဖြစ်အပျက်တွေက နေ အိုင်ဒီယာယူပြီး Sci-Fi, Fantasy ဇာတ်ကားအနေနဲ့ တင်ဆက်ထားပါတယ်။\r\nဇာတ်လမ်းကိုမပြောခင်မှာ တစ်ခုကြိုပြောချင်တာက ဒီကားကို ကြည့်တဲ့အခါ ဒီကားက လက်ရှိကျွန်တော် တို့ ကမ္ဘာထဲမှာဖြစ်နေတာမဟုတ်ပဲ တစ်ခြား Parallel ကမ္ဘာတစ်ခုမှာ ဖြစ်နေတာလို့ သဘောထားပြီး ကြည့်ရင်ပိုပြီးစိတ်ဝင်စားဖို့ ကောင်းပါတယ်။ ဥပမာ ဟယ်ရီပေါ်တာတို့၊ Batman: The Dark Knight Return (Animation) တို့ လိုမျိုးပါ။ ဟယ်ရီပေါ်တာလို တကယ်မရှိတာကို စိတ်ကူးယဉ် ဆန်ဆန် လက်ရှိကမ္ဘာနဲ့ တွဲရိုက်ထားပြီး၊ Batman ကာတွန်းလို့ လက်ရှိ Batman Main stream ကာတွန်းမှာ မဟုတ်တဲ့ ဇာတ်လမ်းကို တစ်ခြားစင်္ကြာဝဠာတစ်ခု (Parallel Universe) အနေနဲ့ ရိုက်ကူးထားပါတယ်။တစ်ချို့က ဒီကားကိုကြည့်ပြီး မကောင်းဘူး၊ ဂျပန် ရိုးရာကို စော်ကားတယ် လို့ ပြောနေတာဟာ အထက်က ကျွန်တော် ပြောသလို သဘောမထားလို့ပါ။ ဒီကားက သမိုင်း ကြောင်းပြန်ပြောပြတဲ့၊ History, Biography မဟုတ်ပါဘူး။ Fantasy ကားပါ။ဇာတ်လမ်းကတော့ ရှေးဟောင်း ဂျပန် နိုင်ငံမှာ စုန်းမတွေ၊ ဝိဇ္ဇာတွေ၊ Giant တွေ ရှိတဲ့ ပုံစံမျိုးနဲ့ ဇာတ်အိမ်တည်ထားပါတယ်။ မင်းသား Keanu Reeves (Kai) က Demon ရဲ့လက်မှာ ကြီးပြင်းလာပြီး၊ Demon တွေက သူ့ကို ပညာစုံ သင်ပေးထားပါတယ်။  ဒါပေမယ့် Kai က သူတို့လက်က ထွက်ပြေးလာခဲ့ပြီး နောက် Samurai တွေရဲ့ ဆရာ Lord Asano က သူ့ကို ကယ်တင်ထားပါတယ်။ ဒီလိုနဲ့ နှစ်တွေကြာလာတဲ့အခါ Lord Asano ရဲ့ သမီးနဲ့ Kai တို့ကြားမှာ သံယောစဉ်ဖြစ်လာကြပေမယ့် ကျန်တဲ့သူတွေက အင်္ဂလိပ်လူမျိုးအဖေ နဲ့ ဂျပန်မိခင်တို့က မွေးဖွားတဲ့သူ (Half-breed) မို့လို့ သူ့ကို ဝိုင်းနှိမ်ကြပါတယ်။တစ်ရက်မှာ ဂျပန် ဘုရင် က သူတို့ရဲ့ နယ်ကို ကြွချီလာပြီး သူတို့နဲ့ ရန်ဖက်နယ်က Lord Kia လည်း ရှေးအစဉ်အလာအတိုင်း သူတို့နယ်ကို ရောက်လာပါတယ်။ Lord Kia ရဲ့အပါးမှာ စုန်းမတစ်ယောက် ရှိပြီး (Rinko Kikuchi, Pacific Rim) သူ့ရဲ့မှော်အစွမ်းနဲ့ Lord Asano ကို အကြိမ်ကြိမ် လုပ်ကြံဖို့ကြိုးစားနေသူဖြစ်ပါတယ်။ သူ့ကို Kai တစ်ယောက်ပဲ ခွဲခြားမြင်နိုင်ပြီး (ဒီလိုမြင်နိုင်တာက လည်း Demon တွေက သင်ထားပေးလို့ဖြစ်တယ်လို့ ယူဆရပါတယ်။) ဒါပေမယ့် Samurai တွေကို သတိပေးတဲ့အခါမှာတော့ ဘယ်သူမှ သူ့စကားကို အရေးမလုပ်ကြပါဘူး။ဒီတစ်ခါမှာတော့ စုန်းမက Lord Asano က Lord Kia ကို ရန်မူတဲ့ပုံစံမျိုး ဖြစ်အောင် ဆေးခပ် လုပ်ကြံပြီး Lord Asano ကို (ကိုယ့်ကိုယ်ကို အဆုံးစီရင်ခြင်းဖြင့်)ဘုရင်က သေဒဏ်ပေးအောင် လုပ်ဆောင်ခဲ့ပါတယ်။ ဒီနေရာမှာ Ronin ရဲ့ အဓိပ္ပာယ်ကို ဇာတ်ကားက Ronin ဆိုတာ Master-less Samurai ဖြစ်ပြီး၊ သူတို့ရဲ့ဆရာသေ သွားတဲ့နောက်မှာ သူ့နောက်လိုက်တွေ အကုန်လုံး Ronin ဖြစ်သွားပြီး သူတို့ရဲ့ နယ်က နေမောင်းထုတ်ခံ လိုက်ရပါတယ်။ Kai ကိုလည်း Dutch တွေဆီကို ကျွန်အဖြစ်ရောင်းခံ လိုက်ပါတယ်။ Lord Asano ရဲ့သမီးကိုလည်း Lord Kia ရဲ့ လက်ထပ်ဖု့ိ ဘုရင်က မှာကြားခဲ့ပြီး၊ အဖေသေဆုံးထားတာကြောင့် ၁ နှစ်အချိန်ပေးပြီး တစ်နှစ်ကြာမှ လက်ထပ်မှာဖြစ်ပါတယ်။\r\nSamurai တွေရဲ့ ခေါင်းဆောင် Oishi ကိုလည်း အကျဉ်းချထားပြီး မင်္ဂလာဆောင်ခါနီးမှ ပြန်လွှတ်ပေးပါတယ်။ဒါကြောင့် Oishi အနေနဲ့ သူ့လူတွေကို ပြန်လိုက်စုပြီး Lord Kia ကို လက်တုန့်ပြန်ဖို့ စီစဉ်ပုံ၊ အရင်က သူ့ရဲ့ မာနတွေကိုချပြီး Kai ကို ပြန်လိုက်ရှာကာ အကူအညီတောင်းရပုံကို ဇာတ်လမ်းစဉ်ရိုက်ကူးထားပါတယ်။ကျွန်တော်အထက်မှာပြောခဲ့သလို Fantasy ကားအနေနဲ့ ပဲသဘောထားကြည်ရင် ဇာတ်ကားကောင်း တစ်ကားဖြစ်ပါတယ်။ ဒီကားထဲမှာ Keanu Reeves ကို မွေးစားခဲ့တဲ့ Demon ဆိုတာ ဂျပန် ဘုန်းကြီး တွေဖြစ်ပြီး၊ ဘုန်းကြီးတွေကို ဆာမူရိုင်းတွေက Demon အဖြစ်သတ်မှတ်ထားပါတယ်။ (ဗုဒ္ဓဘာသာ မထွန်းကားသေးတဲ့အချိန်လို့ယူဆလို့ရသလို၊ တစ်ခြားကမ္ဘာမှာဖြစ်လို့ ဗုဒ္ဓဘာသာလို့ တောင် ယူဆလို့မရပါဘူး)။ ဒါပေမယ့် ဗုဒ္ဓဘာသာ ဘုန်းကြီးတွေနဲ့ ဘုရားဆင်းတုတော် တွေပါနေတာတော့ တစ်မျိုးပါ။ Keanu Reeves ကို ပညာသင်ပေးခဲ့သလို ဘုန်းကြီးတွေကပဲ စုန်းမတွေကို နိုင်တယ်ဆိုတဲ့ သဘောမျိုး တွေ ပါပါတယ်။ ဒါပေမယ့် တစ်ခန်းမှာ မင်းသားက သူ့ကို သင်ပေးတဲ့ Demon တွေက လူသတ်ဖို့သင်ပေးလို့ ထွက်ပြေးလာတယ်လို့လည်း ဆိုပြန်ပါတယ်။ ဘုန်းကြီးတွေက လူသတ်တာမျိုး၊ မကောင်းမှုလုပ်တာမျိုးတွေ မဟုတ်ပါဘူး။ Samurai တွေက အထင်လွဲနေတဲ့ အနေနဲ့လည်း ပြထားတာဖြစ်ပါတယ်။ တကယ့် ဂျပန်မှာလည်း အဲ့ဒီအချိန်မှာ ဗုဒ္ဓဘာသာ မထွန်းကားသေးပါဘူး။ ၁၃ရာစုနောက်ပိုင်းမှ ထွန်းကားတယ်လို့ သိရပါတယ်။ရုပ်ရှင်ကားကောင်းတစ်ကားပါ။ Graphic Effect တွေကောင်းမွန်သလို၊ Keanu Reeves ရဲ့ တစ်ချို့ Fight Scene တွေက Computer Graphic ဖြစ်ပြီး များသောအားဖြင့်ကတော့၊ သဘာဝသိုင်းကွက်တွေ ဖြစ်ပါတယ်။ Matrix ဇာတ်ကားထဲက Neo vs Agent Smith ဇာတ်ဝင်ခန်းလောက် မကောင်းပေမယ့် အဲ့ဒီကားကိုပြန် အမှတ်ရစေပါတယ်။ ဇာတ်ရှိန် ကတော့ အတက် အကျ သိပ်မမှန်သလို၊ ဇာတ်လမ်း သရုပ်ဖော်ပုံလည်း အနည်းငယ် ညံ့ပါတယ်။ ဥပမာ Samurai ခေါင်းဆောင် အဓိက ရန်သူကို မသတ်ပဲ ကျွင်းထဲ ၁နှစ်ပစ်ချထားပြီးမှ ပြန်လွှတ်ပေးတာမျိုး၊ (သူ့ပါသူထွက်ပြေးတယ်ဆိုရင်တောင် ကြည့်ကောင်းဦးမှာပါ) တွေက ဇာတ်လမ်းရဲ့အားနည်းချက်တွေပါ။Keanu Reeves ကို ဒီကားနဲ့ နာမည်ပြန်တက်လာဖို့ မျှော်လင့်ထားပေမယ့် ထင်သလောက်မဖြစ်လာပါဘူး။ အထူးသဖြင့် အချစ်ခန်းတွေ၊ ဝမ်းနည်းတဲ့အခန်းတွေမှာ သူ့ရဲ့ မျက်နှာသေကြီးနဲ့ သရုပ်ဆောင်တာတွေ၊ ဒိုင်ယာလော့အချို့ သိပ်မပီပြင်တာတွေကြောင့် သိပ်တော့ အားမရသေးပါဘူး။ အက်ရှင် အခန်းတွေ မှာတော့ သရုပ်ဆောင်ပီပြင်ပါတယ်။ ဇာတ်လမ်းကိုသူနဲ့ Oishi က ဆွဲခေါ်သွားတာဖြစ်ပြီး Oscar Nominated မင်းသမီး Rinko Kikuchi ကလည်း ဗီလိန်နေရာက ပီပီပြင်ပြင် သရုပ်ဆောင်ထားတာကို တွေ့ရပါတယ်။ တစ်ခုပဲပြောချင်တာက Rinko Kikuchi က အဓိက ဗီလိန်ဆိုပေမယ့် ဇာတ်ကားအစပိုင်းမှာ Lord Kia ရဲ့ သူရဲကောင်းအဖြစ် Samurai ဝတ်စုံဝတ် အရပ်ခုနစ်ပေနီးပါးရှိတဲ့ Samurai တစ်ယောက်ကို Keanu Reeves နဲ့ ချခိုင်းပြီး အနိုင်အရှုံးမကွဲ ပြားပါဘူး။ တကယ်ဆို ဇာတ်သိမ်းပိုင်းမှာ သူနဲ့ရော Witch နဲ့ပါ ချခိုင်းရင် ပိုကောင်းမှာဖြစ်ပေမယ့် အဲ့ဒီလူဆိုးကို သတ်လိုက်တဲ့ပုံစံကို သိပ်သဘောမကျပါဘူး။ ဒါဒီနှစ်ထဲမှာ Out of the Furnace ပြီးရင် ဗီလိန်ကို မင်းသားနဲ့ သေချာမတွေ့ပေးတဲ့ ဒုတိယမြောက် ကားဖြစ်ပါတယ်။မိသားစုတူတူကြည့်နိုင်ပါတယ်။ Rated PG-13 ပါ။ (No Sex, No Nudity) မိသားစု အပန်းပြေကြည့်သင့်တဲ့ကားတစ်ကားဖြစ်ပါတယ်။ Keanu Reeves ရဲ့ ပရိတ်သတ်တွေအတွက်ကတော့ ၅ နှစ်အတွင်းမှာ ပထမဆုံး ရုပ်ရှင်ကောင်းတစ်ခုမှာ ပြန်ကြည့်ရမှာဖြစ်လို့ လက်မလွှတ်သင့်ပါဘူး။ ဒီကားကနေစလို့ နောက်ပိုင်း ကားတွေ ပိုကောင်းသွားပါစေလို့ပဲ မျှော်လင့်ရပါတယ်။","year":2013,"imdb":6.3,"comment":true,"rating":0,"duration":"128 min","downloadas":"1","playas":"1","classification":"1.24 GB","image":"https://app.zchannelmovie.com/uploads/cache/poster_thumb/uploads/jpg/18c5550cb10beac6fdd5fa2fc2fe0708.jpg","cover":"https://app.zchannelmovie.com/uploads/cache/cover_thumb/uploads/jpg/8b098808ed0cfb4df556a0f53c288c19.jpg","genres":[{"id":1,"title":"Action"}],"trailer":{"id":4705,"type":"youtube","url":"https://youtu.be/DEoDulGTElE"},"sources":[{"id":4704,"type":"mp4","url":"https://f002.backblazeb2.com/file/zstorage501/movies/2013/47.Ronin..2013..(MM.Sub).mp4"}]},{"id":767,"type":"movie","title":"Ae Dil Hai Mushkil","description":"IMDb 5.8 နဲ့ Time India မှာ 3.5/5 ထိရရှိထားတဲ့အချစ် အလွမ်း ဇာတ်ကားကြီးနဲ့ မိတ်ဆက်ပေးပါရစေ  ဒါရိုက်တာကြီး Karen Johar ရဲ့ ဇာတ်ကွက်နိုင်နင်းမှုကို ခဏထား ဒီဇာတ်ကားမှာ\r\nအဓိက သရုပ်ဆောင်ဖြစ်တဲ့ Ranbir Kapoor ရဲ့ သရုပ်ဆောင်ချက်တွေကို ချီးမွမ်းပါရစေအစက ရုပ်ချော၍ မင်းသားဖြစ်လာခဲ့သည် ထင်ခဲ့မိသော်လည်း ဤဇာတ်ကားတွင်တော့အလွန်တရာ ဇာတ်ရုပ်ကျလှပေသည်လွတ်လပ်ပေါ့ပါးသော လူငယ် အချစ်ကြီးသော လူငယ် အရွဲ့တိုက်တတ်သောစိတ် စသည်ကိုပေါ်လွင်အောင်သရုပ်တောင်ပြသွားလေသည်PK မင်းသမီး Anuskha ကတော့ ပြောစရာမရှိ လိုက်ဖက်ညီအောင်သရုပ်ဆောင်ပြသွားသည်ဒီနှစ် ဘောလိဝုဒ်အကယ်ဒမီမှာတောင် Ranbir က ဒီကားနဲ့SRK ကFan နဲ့ ယှဉ်ပြိုင်ကြမယ်တောင် ထင်မိလေ၏တချို့ ချွင်းချင်အနေဖြင့် မိတ်ကပ် ဆံပင်တုပြုလုပ်မှုအနည်းငယ်သိသာတာဘောလိဝုဒ်စံအတိုင်း ဇာတ်ဝင်သီချင်းများခြင်းက လွဲ၍ အကုန် ကောင်း၏ ကြာမြင့်လှသောအချ်န်နှစ်နာရီခွဲကာလ မှာ မပျင်းအောင် ဟာသ အချို့နှင့် ဆွဲဆောင်သွားပေလိမ့်မည်နောက် ချီးကျူးစရာမှာ ဇာတ်ညွှန်း နှင့် နောက်ခံတေးဂီတ ဇာတ်ဝင်သီချင်းများ အစပ်ဟပ် အလွန်ကောင်း၏ကျွန်တော်အကြိုက်ဆုံး ဇာတ်ညွှန်းစာသားမှာ Ranbir မှ Sharukh ကိုမေးသောစာသား( Ranbir-If you are wait someone who will never love to you,how’s you feel?Sharukh -Yes,I am happy, its most wonderful thing in world,coz I love herRanbir-ခင်ဗျား ဟာ ခင်ဗျားကိုမချစ်တဲ့သူကို စောင့်နေရမယ်ဆိုခင်ဗျား ဘယ်လိုခံစားရမလဲSharukh -အင်း ပျော်တာပေါ့ကွာအဲဒါက ကမ္ဘာပေါ်မှာ အကောင်းဆုံး အရာလေ,ဘာကြောင့်လဲဆိုတော့ ငါသူ့ကိုချစ်လို့ပဲ )အဆုံးသတ်နေနှင့် ညွှန်းဆိုရလျှင် လူငယ်ဆန်ဆန် Romance အလွန်ကြိုက်သူများအနေနဲ့ ကြည့်ရှုသင့်ကြောင်း ညွှန်းဆိုပါရစေ","year":2016,"imdb":5.8,"comment":true,"rating":4.3,"duration":"158 min","downloadas":"1","playas":"1","classification":"0.98 GB","image":"https://app.zchannelmovie.com/uploads/cache/poster_thumb/uploads/jpg/0674ee23222ed5ca9876228fd2841ce0.jpg","genres":[{"id":12,"title":"Bollywood (India)"},{"id":13,"title":"Drama"}],"trailer":{"id":4703,"type":"youtube","url":"https://youtu.be/Z_PODraXg4E"},"sources":[{"id":4702,"type":"mp4","url":"https://f002.backblazeb2.com/file/zstorage501/movies/2016/Ae.Dil.Hai.Mushkil.(.2016.).mp4"}]},{"id":766,"type":"movie","title":"Ready Player One","description":"ဟောလိဝုဒ်ရုပ်ရှင်လောကမှာ ရုပ်ရှင်တစ်ကားရိုက်တိုင်း အမြင်သစ်တစ်မျိုးနဲ့တင်ဆက်တတ်တဲ့ စတီဗင်စပီးဘတ်က ၂၀၁၈ မှာတော့ 80s, 90s born တွေအတွက်အမှတ်တရဖြစ်သွားစေမယ့် ကားတစ်ကားကို ချပြသွားခဲ့ပါတယ်။ဒီ Ready Player One ရုပ်ရှင်ဟာ Ernest Cline ရဲ့ Ready Player One ဆိုတဲ့ဝတ္ထုကိုအခြေခံရိုက်ကူးထားတာဖြစ်ပြီး ဒီရုပ်ရှင်ဟာ ယနေ့ခေတ်မှာ လူသုံးများလာတဲ့ VR စနစ်နဲ့1980 ကနေ 2000 ခုနှစ်ကြားမှာ ရေပန်းကျော်ကြားခဲ့တဲ့ ရုပ်ရှင်၊ ကာတွန်း၊ စာအုပ်၊ ဂိမ်း၊ သီချင်းတို့ကိုအချိုးကျကျ ပေါင်းစပ်ပြသနိုင်ခဲ့တဲ့အတွက် ဝေဖန်ရေးဆရာတွေချီးကျူးထားတဲ့ ရုံတင်ကားကောင်းတစ်ကားဖြစ်ပါတယ်။၂၀၄၅ ခုနှစ်အရောက်မှာ ကမ္ဘာပေါ်က လူတွေဟာ လက်တွေ့ဘဝက ပြဿနာတွေကို ရင်ဆိုင်ဖြေရှင်းဖို့မကြိုးစားတော့ပဲ ထွက်ပေါက်အဖြစ် လွတ်မြောက်ဖို့နေရာတစ်ခုအဖြစ် အိုအေစစ်လို့ခေါ်တဲ့ Visual Worldထဲမှာပဲ အိပ်ချိန်၊ စားချိန်နဲ့ သန့်စင်ခန်းသွားချိန်တွေကလွဲလို့ ကျန်တဲ့အချိန်တွေကို ကုန်ဆုံးကြပါတော့တယ်။ဒီ အိုအေစစ်ကြီးကို ဖန်တီးခဲ့သူကတော့ ဂျိမ်းစ်ဟာလီဒေးဖြစ်ပြီး သူမသေဆုံးခင် အိုအေစစ်ထဲမှာ အီစတာဥလို့ခေါ်တဲ့ပစ္စည်းတစ်ခုကိုထားခဲ့ပါတယ်။အဲ့ဒီဥကို ရှာဖွေတွေ့ရှိသူဟာ ဟာလီဒေးရဲ့ ပိုင်ဆိုင်မှုတွေအားလုံးနဲ့ အိုအေစစ်ကိုထိန်းချုပ်ခွင့်ပါ ရရှိမှာဖြစ်တဲ့အတွက် အိုအေစစ်ထဲက လူအားလုံးက အဲ့ဒီဥကို အသည်းအသန်လိုက်ရှာကြပါတော့တယ်။\r\nအဲ့ဒီလိုလိုက်ရှာနေကြတဲ့သူတွေထဲမှာ Ready Player One ရုပ်ရှင်ရဲ့ အဓိကဇာတ်ကောင်ဖြစ်တဲ့ ဝိတ်ဝက်စ်လဲ ပါဝင်သလိုIOI ဆိုတဲ့ ကုမ္ပဏီကြီးကလဲ အဲ့ဥနောက်ကိုသဲသဲမဲမဲလိုက်နေတာပါ။ဥကို ရဖို့အတွက် သော့ ၃ ချောင်းအရင်ရှာရမှာဖြစ်ပြီးသဲလွန်စတွေကို ဘယ်လိုအဖြေဖော်ကြမလဲ၊ဘယ်သူ အဲ့ဥကိုရသွားမလဲ၊ဟာလီဒေးရဲ့ အစီအစဉ်ကရော ဘယ်လိုလဲဆိုတာတော့ပရိသတ်တွေအနေနဲ့ ဖိုင်ဆိုဒ်အကြီးကိုသာဒေါင်းပြီး အလှပဆုံး CGI တွေနဲ့ အမြူးကြွဆုံး 80s Rock သီချင်းတွေပါဝင်တဲ့ ဒီရုပ်ရှင်ကို ဇိမ်နဲ့ခံစားကြည့်ရှူလိုက်ကြပါ။ဒီရုပ်ရှင်ထဲမှာ 80s, 90s ခေတ်က ရုပ်ရှင်တွေ ဂိမ်းတွေ သီချင်းတွေကို ကိုးကားထားတာတွေ မရေတွက်နိုင်အောင်ပါဝင်ပါတယ်။ဇာတ်ကောင်တွေရဲ့ ဒိုင်ယာလော့တွေကအစ ဒီကိုးကားချက်တွေမပါရင် မပြီးဘူးလို့တောင် ပြောလို့ရလောက်တဲ့အထိပါပဲ။ဖြစ်နိုင်ရင် ဒီရုပ်ရှင်ကို နှစ်ခေါက်တော့အနည်းဆုံးကြည့်စေချင်ပါတယ်။ပထမတစ်ခေါက် ဇာတ်လမ်းကိုခံစားပြီးကြည့်ပါ။ဟောင်းပေမယ့်ကောင်းနေဆဲ သီချင်းတွေကို ခံစားကြည့်ပါ။ဒုတိယတစ်ခေါက်မှာ သူတို့ရဲ့ကိုးကားချက်တွေကိုခံစားကြည့်ပါ။ကိုးကားချက်တွေကို ရှာဖွေရလွယ်အောင် ဘာသာပြန်ကတည်းက ကွင်းစကွင်းပိတ်နဲ့ ရှင်းချက်တွေထည့်ပေးထားပြီးရုပ်ရှင်၊ ဂိမ်း နာမည်တွေကို English လိုသာ တမင်ချန်ထားပေးခဲ့ပါတယ်။အားလုံးပဲ ဒီရုပ်ရှင်ကို ၂ ခါမြောက်ကြည့်ပြီးရင် Google ဂုဏောအနေန္ဒောနိုင်ကြပါစေ။တစ်ခုတော့ပြောပါရစေ။Ready Player One ရုပ်ရှင်ဟာ ဖျော်ဖြေရေးဇာတ်ကားသက်သက်မဟုတ်ပါဘူး။သိပ်မကြာတော့တဲ့အနာဂတ်မှာ ကျွန်တော်တို့ကိုယ်တိုင်ကြုံတွေ့ရနိုင်တဲ့ နည်းပညာလွှမ်းမိုးမှုပြဿနာတွေကို ကြိုပြီး သတိထားကြဖို့အတွက်၊ ကာကွယ်နိုင်ဖို့အတွက်၊ Pop Culture တွေကိုလဲ ထိန်းသိမ်းနိုင်ဖို့အတွက်ရည်ရွယ်ပြီး တင်ဆက်ထားတဲ့ ဇာတ်ကားတစ်ကားပါ။လူကြီးတွေအနေနဲ့ ဒီရုပ်ရှင်ကိုကြည့်ပြီး ဂျိမ်းစ်ဟာလီဒေးကို နှစ်သက်ကြမှာဖြစ်သလို လူငယ်တွေကလဲရဲ ၅ ဖော်ကို သဘောကျသွားကြမှာသေချာပါတယ်။ပြီးတော့ အမျိုးသမီးချောများ မမေ့ပါနဲ့၊ ဒီရုပ်ရှင်မှာ မိုရီဆာကီဝင်း (အဝင်း) ပါပါတယ်ခင်ဗျ။","year":2018,"imdb":7.5,"comment":true,"rating":5,"duration":"140 min","downloadas":"1","playas":"1","classification":"1.19 GB","image":"https://app.zchannelmovie.com/uploads/cache/poster_thumb/uploads/jpg/c8e973c64bb399674bf45d0a0d5ecfdb.jpg","cover":"https://app.zchannelmovie.com/uploads/cache/cover_thumb/uploads/jpg/624adf87fac8a2c8669e508778f6de74.jpg","genres":[{"id":8,"title":"Sci-Fi"}],"trailer":{"id":4701,"type":"youtube","url":"https://youtu.be/dtwpjnuaVTE"},"sources":[{"id":4700,"type":"mp4","url":"https://f002.backblazeb2.com/file/zstorage501/movies/2018/Ready.Player.One..2018..(MM.Sub).mp4"}]},{"id":763,"type":"movie","title":"Hulk","description":"Hulk (2003) ကတော့ Hulk ရဲ့ Origin ကိုသီးသန့်ရိုက်ကူးထားဖြစ်ပြီး Solo သဘောမျိုး ထွက်ရှိထားတာပါ။MCU နဲ့ တိုက်ရိုက်ကြီး ဆက်နွယ်မှုမရှိပေမယ့် Hulk ရဲ့ Origin ကိုတော့ မြည်းစမ်းဖို့ ကြည့်သင့်ပါတယ်။","year":2003,"imdb":5.6,"comment":true,"rating":5,"duration":"138 min","downloadas":"1","playas":"1","classification":"1.16 GB","image":"https://app.zchannelmovie.com/uploads/cache/poster_thumb/uploads/jpg/45f568ea728e5a227181e219a88f3394.jpg","genres":[{"id":2,"title":"Adventure"},{"id":4,"title":"Super Hero"}],"trailer":{"id":4668,"type":"youtube","url":"https://youtu.be/LAZOmwkRq_A"},"sources":[{"id":4667,"type":"mp4","url":"https://f002.backblazeb2.com/file/zstorage501/movies/Marvel.DC/Hulk(2003).mp4"}]},{"id":762,"type":"movie","title":"Commando 3","description":"ဇာတ်လမ်းအကျဉ်း :-\r\nBollywood ရုပ်ရှင်မင်းသားကြီး Vidyut Jammwal\r\n၏ စစ်မှန်သော အက်ရှင်ဇာတ်ကားကြီးဖြစ် ပါသည်။\r\nCommando 1 & 2 ကြည့်ထားသူများအတွက်တော့\r\nမင်းသားကြီး၏ ကိုယ်တိုင် စစ်စစ်သရုပ်ဆောင် ထား\r\nသော အက်ရှင်ကို သိရှိခဲ့ကြပြီးဖြစ်သည်။ ယခုထွက်\r\nရှိသော Commando 3 ဇာတ်ကားမှာ ယခင်ဇာတ်\r\nကားတွေထက်ပိုသာသောအက်ရှင်အသစ်များကို\r\nကြည့်ရူရမည်ဖြစ်သည်။\r\n\r\nဇာတ်လမ်းမှာ လူငယ်ကောင်လေးသုံးယောက် သင်\r\nတန်းတက်ရန် India သို့သွားခဲ့သည်။ သို့ သော် သူ\r\nတို့သုံးယောက်ကို အတုအယောင်ဆောင် အကြမ်း\r\nဖက်နှိမ်နင်းရေးအဖွဲ့က Passbook အတုကိုင်ဆောင်\r\nသည်ဟု စွပ်ဆွဲကာ ဖမ်းခေါ်¬သွားကြသည်။ဖမ်းသွား\r\nသူမှာဘယ်သူမှမသိပေ။ ထို အကြမ်းဖက် သမားသည်\r\nထိုကလေး ငယ် (3)ဦးကို သွေထိုးဖျားယောင်ပြီး India\r\nနိုင်ငံတွင် အကြမ်းဖက်ရန် စေခိုင်းတော့ သည်။ နိုင်ငံ\r\nတော်အနေနဲ့ ထိုအကြမ်းဖက်သမားသည် Londonတွင်\r\nနေ၍ ကြိုးကိုင်လှုပ်ရှားသည်ကိုသာ သိသည်။ Karan\r\nSingh Dogara (Vidut Jamwal)သည် ထိုအကြမ်းဖက်\r\nခေါင်းဆောင်ကို ဖမ်းရန် London ကိုသွားခဲ့သည်။ သူနဲ့\r\nအတူ British Intelligence ဌာနမှ Bhavnareddy,\r\nMalika Sood and Armaan Akhtar တို့ ပါဝင်လှုပ်ရှား\r\nကြတော့သည်။ အကြမ်းဖက်ခေါင်းဆောင် ၏ အစီစဉ်မှာ\r\nIndia နိုင်ငံတွင် ဗုံးထောင်ဖောက်ခွဲ၍ အကြမ်းဖက်ရန်\r\nဖြစ်သည်။\r\n\r\n1.ဤအဖြစ် ပျက်များအားလုံးကို ကာကွယ်ရန် Vidyut Jammwal\r\nlနှင့်သူ့အဖွဲ့သားများ လုပ်ဆောင်နိုင်ကြမည်လား?\r\n\r\n2. ဗုံးထောင် သောနေရာနှင့် အချိန်ကိုသိနိုင်ကြမည်လား?\r\n\r\n3. ဖမ်းဆီးခေါ်ဆောင်ခံခဲ့ရသော လူငယ်သုံးယောက်\r\nတည်း ဟုတ်ရဲ့လား?\r\n\r\n4. တခြားဖမ်းဆီးခံရသော လူများလည်းရှိကြမည်လား?\r\nစသည့် ဇာတ်ကွက်မေးခွန်းများ၏အဖြေကို ရင်ခုန် စိတ်\r\nလှုပ်ရှားဖွယ်ကောင်းသော အက်ရှင်ဇာတ်ကွက် စစ်စစ်\r\nဖြင့် ကြည့်ရူရမည်ဖြစ်ပါသည်။","year":2019,"imdb":5.5,"comment":true,"rating":3.3,"duration":"133 min","downloadas":"1","playas":"1","classification":"949 MB","image":"https://app.zchannelmovie.com/uploads/cache/poster_thumb/uploads/jpg/bca2a6d660dc24dadf8368f884620326.jpg","genres":[{"id":1,"title":"Action"},{"id":12,"title":"Bollywood (India)"}],"sources":[{"id":4666,"type":"mp4","url":"https://f002.backblazeb2.com/file/zstorage501/movies/2019/Commando.3.2019.mp4"}]},{"id":761,"type":"movie","title":"Commando 2","description":"ကွန်မန်ဒို ဇာတ်ကားမှာ အက်ရှင်စတန့် အလန်းစားတွေနဲ့ ပရိတ်သတ်ရင်ထဲရောက်ရှိခဲ့တယ့်\r\nမင်းသားဗရွတ်ဂျမဝဲလ်က ဒီတခါလည်း အမှန်အကန် နောက်တကားနဲ့ ပရိတ်သတ်အရှေ့ ရောက်ရှိလာခဲ့ပါပြီ။အိန္ဒိယ အစိုးရဟာ ငွေကြေးဖျက်သိမ်းရေး\r\nအစီစဉ်ကို အကောင်ထည်ဖော်ခဲ့ပြီး တနိုင်ငံလုံးမှာရှိတယ့် ငွေမည်းတွေအားလုံးကို ဖျက်သိမ်းခဲ့ပါတော့တယ့်ဒါပေမယ့် ပြည်ပမှာ ငွေမည်းကို ငွေဖြူအဖြစ်ခဝါချပြီး သိမ်ဆည်းထားတယ့် ပိုက်ဆံတွေကတော့ ရှိနေဆဲပါပဲ့ဒီကိစ္စကို နောက်ကွယ်က လုပ်ကိုင်ပေးနေတယ့် ဗစ်ကီချန်ဒဟ်ကို မလေးရှားမှာ ဖမ်းမိခဲ့ပေမယ်\r\nမြို့တော်ဝန်ရဲ့သားကိုယ်တိုင်က ဒီထဲမှာ ပါဝင်ပတ်သက်နေလို့ တရားဝင်မကြေညာရဲပါဘူးမြို့တော်ဝန်က သူ့အစီစဉ်အတိုင်း သူ့စိတ်ကြိုက်လူတွေကို ရွေးပြီး ဗစ်ကီချန်ဒဟ်ကို အိန္ဒိယကို ပြန်ခေါ်ဖို့လုပ်ပါတော့တယ်ဒီအချိန်မှာတော့ အထူးတပ်သား ကရန်ဟာ\r\nမြို့တော်ဝန်အကြံတွေကို သိပြီး အဖွဲ့ထဲကို သူပါဝင်ခဲ့ပါတယ့်ဗစ်ကီချန်ဒဟ်ကို အိန္ဒိယကိုခေါ်လာနိုင်မလား့မြို့တော်ဝန်ရဲ့ အကြံတွေကော\r\nအောင်မြင်ပါ့မလား့ပြည်ပရောက်နေတယ့် ငွေမည်းတွေကကော ပြန်ရပါ့မလား ဆိုတာကိုတော့ ပရိတ်သတ်ကြီးကပဲ ဆက်လက်ရှု့စားလိုက်ပါဦး့ဇာတ်လမ်းတခုလုံးက လှည့်ကွက်အပြည့်နဲ့မို့ တကယ်ကို စိတ်ဝင်စားစရာ ကောင်းလှပါတယ်(ဇာတ်လမ်းအညွှန်းနဲ.ဘာသာပြန်သူကတော့ ကိုဇော်ထူးဖြစ်ပါတယ်)","year":2017,"imdb":5.2,"comment":true,"rating":5,"duration":"144 min","downloadas":"1","playas":"1","classification":"0.99 GB","image":"https://app.zchannelmovie.com/uploads/cache/poster_thumb/uploads/jpg/01f977e927f8b73a8101beec7b2007ab.jpg","genres":[{"id":1,"title":"Action"},{"id":12,"title":"Bollywood (India)"}],"sources":[{"id":4665,"type":"mp4","url":"https://f002.backblazeb2.com/file/zstorage501/movies/2017/Commando.2.2017.mp4"}]},{"id":760,"type":"movie","title":"Commando","description":"ဒီတခါတော့\r\nBollywoodပရိတ်သတ်တွေအတွက်\r\nအလန်းစား စတန့်တွေနဲ့ အက်ရှင်ခပ်ကြမ်းကြမ်းလေးကို\r\nတင်ဆက်ပေးထားပါတယ်။ဒီကားတွေရဲ့ မင်းသား ဗီရွတ်ဂျမာဝဲလ်က စတန့်ခန်းတွေကို ကိုယ်တိုင်ကြိုးစားသရုပ်ဆောင်ထားတာလည်း ဖြစ်ပါတယ်။ဇာတ်လမ်းကတော့\r\nအိန္ဒိယစစ်တပ်ရဲ့ အထူးတပ်သားတွေဟာ လေ့ကျင့်ရေးဆင်းရင်း\r\nမုန်တိုင်းမိပြီး တရုတ်နယ်စပ်မှာ လေယာဉ်ပျက်ကျခဲ့ပါတယ်။တပ်သားတွေထဲက ကရန်ဟာ တရုတ်စစ်တပ်ရဲ့ ဖမ်းစီးခြင်းကိုခံခဲ့ရပြီး\r\nတရုတ်အစိုးရကလည်း သူ့ကို စပိုင်တယောက်လို့ထင်ပြီး အမျိုးမျိုးညဉ်းပန်းနှိပ်စက်ပြီး စစ်ကြောပါတော့တယ့်တဖက်မှာလည်း အိန္ဒိယအစိုးရက နိုင်ငံရေးပြသနာတွေတက်မှာစိုးလို့\r\nသူ့ကို မကယ်တော့ပါဘူး့တရုတ်လက်လွတ်မြောက်ဖို့ ကြိုးစားခဲ့ရတယ့် ကွန်မန်ဒို တပ်သားကရန်ဟာ\r\nနယ်စပ်မှာ ဂိုဏ်းစတားတယောက်လက်က ထွက်ပြေးနေရတယ့် မိန်းကလေးတယောက်ကို ကူညီပေးလိုက်ရင်း ပြသနာအကြီးအကျယ်တတ်ပါတော့တယ်။ဂိုဏ်စတားတွေလက်ထဲက မိန်းကလေးကို ကရန်တယောက် ဘယ်လိုကယ်တင်မလဲဆိုတာတော့\r\nပရိတ်သတ်ကြီးပဲ ကြည့်လိုက်ပါတော့အက်ရှင်ကြိုက် ပရိတ်သတ်တွေအနေနဲ့ လက်အလွတ်မခံသင့်ပါဘူး့(ဘာသာပြန်သူကတော့ ကို စည်သူအောင်ပဲဖြစ်ပါတယ်)","year":2013,"imdb":6.1,"comment":true,"rating":2.5,"duration":"124 min","downloadas":"1","playas":"1","classification":"903 MB","image":"https://app.zchannelmovie.com/uploads/cache/poster_thumb/uploads/jpg/83d13738063ad7858349f8832ff75992.jpg","genres":[{"id":1,"title":"Action"},{"id":12,"title":"Bollywood (India)"}],"trailer":{"id":4664,"type":"youtube","url":"https://youtu.be/yKQRgidjk-0"},"sources":[{"id":4663,"type":"mp4","url":"https://f002.backblazeb2.com/file/zstorage501/movies/2013/Commando.2013.mp4"}]},{"id":758,"type":"movie","title":"World Famous Lover","description":"လူ့ဘ၀ဆိုတာဟာ အခန်းပေါင်းများစွာနဲ့ဖွဲ့စည်းထားတဲ့ ဇာတ်လမ်းတစ်ပုဒ်ပါ။ဘယ်နေရာမှာ ဘယ်သူနဲ့တွေ့ခဲ့တယ် ၊ ဘယ်မှာနေခဲ့တယ် ၊ ဘာတွေလုပ်ခဲ့တယ်ဆိုတဲ့ ခေါက်ရိုးကျိုးအခန်းတွေမဟုတ်ပဲ ဘယ်သူနဲ့ချစ်ခဲ့တယ် ဘယ်သူ့ကို ချစ်ခဲ့တယ် ၊ ဘယ်လိုအသည်းကွဲခဲ့တယ်ဆိုတဲ့ သူမတူတဲ့ အချစ်ဇာတ်လမ်းလေးတွေတော့ ကိုယ်စီရှိကြမယ် ထင်ပါရဲ့။ဒီဇာတ်လမ်းလေးထဲမှာတော့ မင်းသား(ဂေါ်သမ်)ဟာ စာရေးဆရာဖြစ်လိုသူ၊ သူ့ချစ်သူ(ယမနီ – ယမင်းရုပ်လို့ပဲ ဆိုပါစို့)ရဲ့အထောက်အပံ့ကို ယူ ၊ ချစ်သူနဲ့ အတူနေပြီး စာရေးဖို့ကြိုးစားနေသူပေါ့။ဒါပေမယ့်လည်း စာရေးဆရာတို့ ၊ ပန်းချီဆရာတို့လို အနုပညာမှော်ဝင်စားတတ်သူတွေဟာ ချစ်သူအပေါ်ထားရှိရမယ့် တာဝန် ၊ ချစ်သူအပေါ် ဂရုစိုက်ရမယ့်၀တ္တရားတွေကို မဆိုထားနဲ့ဦး ။\r\nစားဖို့ အိပ်ဖို့တောင် မေ့လျော့နေတတ်ကြသူတွေလေ…။ ယမနီအတွက်တော့ နေ့စဉ်အလုပ်သွား၊ ပြန်လာတိုင်း ဆေးလိပ်တစ်ဖက်၊စာအုပ်တစ်ဖက်နဲ့ ယောကျ်ားယမနီလုပ်ပေးခဲ့တဲ့ စားသောက်ဖွယ်ရာတွေကို ကာတွန်းကြည့်ပြီးထိုင်စားနေတဲ့ လင်ယောကျ်ားကို မြင်ရလိုက်ညဘက်အိပ်ယာဝင်တိုင်း သန္ဓေတားဆေးသောက်ရလိုက်နဲ့ ဘာတိုးတက်မှုမှ ရှိမလာတဲ့ လင်ယောကျ်ားအပေါ် စိတ်ကုန်လာခဲ့ပါတယ်။ဒီတော့ အချိန်တွေကြာလာတာနဲ့အမျှ ချစ်သူနှစ်ဦးကြား ပဋိပက္ခတွေဖြစ်လာပြီး ဘယ်လိုမှ ညှိနှိုင်းလို့မရတဲ့အဆုံး…. ပြတ်စဲကြရတော့တယ်….။ချစ်သူနဲ့အတူနေချိန်မှာ ခေါင်းထဲက ဘာအကြောင်းအရာမှမထွက်သလို၊ နှလုံးသားထဲကနေလည်း ဘာမှဆွဲထုတ်လို့မရခဲ့တဲ့ ဂေါ်သမ်ဟာ စာတွေရေးဖြစ်လာခဲ့တယ်။သူရေးလိုက်တဲ့ ဇာတ်လမ်းတိုင်းမှာ သူကိုယ်တိုင် ဇာတ်လိုက်အဖြစ်နဲ့ ခံစားပြီး ရေးလိုက်တာတွေကြောင့် သူ့ဇာတ်လမ်းတွေဟာ သူ့စရိုက်သူ့စိတ်ထားနဲ့ အချစ်အပေါ် သူမြင်တဲ့အမြင်တွေနဲ့ ပြည့်နှက်နေတော့တယ်။ဒီဇာတ်လမ်းကို သရုပ်ဆောင်ထားတဲ့သူက Geetha Govindam , Dear Comrade တို့လို ဇာတ်ကားလေးတွေကို ပရိတ်သတ်ရင်ထဲကို ရောက်လာခဲ့သူ Vijay Deverakonda ဖြစ်ပြီးမင်းသမီးကလည်း အိန္ဒိယဇာတ်ကားပရိတ်သတ်တွေနဲ့ မစိမ်းလှတဲ့ ပုရိသတို့ရဲ့ အသည်းကျော်လေး Raashi Khanna ဖြစ်ပါတယ်။","year":2020,"imdb":4.7,"comment":true,"rating":3.3,"duration":"154 min","downloadas":"1","playas":"1","classification":"1.20 GB","image":"https://app.zchannelmovie.com/uploads/cache/poster_thumb/uploads/jpg/019775a6fafffcee909536b84c28ffb3.jpg","genres":[{"id":12,"title":"Bollywood (India)"},{"id":13,"title":"Drama"}],"sources":[{"id":4489,"type":"mp4","url":"https://f002.backblazeb2.com/file/zstorage501/movies/2020/(zCM).World.Famous.Lover.2020.720p.NF.WEB-DL.mp4"}]},{"id":757,"type":"movie","title":"Need for Speed","description":"အသစ်ထွက် Need For Speed (2014) ရုပ်ရှင်သွားကြည့်ဖြစ်ခဲ့တယ်။ ဇာတ်ကားက ပြိုင်ကား Crazy တွေအရမ်းကြိုက်နှစ်သက်မယ့် ဇာတ်ကားပုံစံပါ။ Fast & Furious ဇာတ်ကားထက်တောင် လန်းပါသေးတယ်။ ဒါကမှ တကယ့်ပြိုင်ကားဇာတ်လမ်းစစ်စစ်လို့ပြောရမှာပါ။ ဇာတ်ကားတစ်ခုလုံး ပြိုင်ကားတွေယှဉ်ပြိုင်မောင်းနှင်တဲ့ အပေါ်မှာပဲ ဇာတ်အိမ်တည်ဆောက်ထားပြီး စိတ်ရှုပ်ရှားဖွယ် Action ၊ ဝမ်းနည်းဖွယ် ဇာတ်ဝင်ခန်း ၊ ဟာသပုံစံဇာတ်ဝင်ခန်းများနဲ့ကောင်းမွန်လှတဲ့ ဒီဇာတ်ကားမှာ ဒေါ်လာသန်းချီတန်တဲ့တန်ဖိုးကြီးပြိုင်ကားအစုံနဲ့ မောင်းနှင်ယှဉ်ပြိုင်မှုတွေကို\r\nဒီဇာတ်ကားမှာတွေ့မြင်ရမှာပါ။ ဇာတ်ကားအစပိုင်း တန်ဖိုးကြီး ပြိုင်ကားသုးံစီးပြိုင်ရာမှာ ပြိုင်ကားတစ်စီးမီးလောင်သွားတဲ့အခန်းဆို တကယ်အသက်ဝင်လွန်းလို့ ကားတိုက်မီးလောင်ပြီးသေသွားတဲ့ Fast & Furious မင်းသား Paul Walker ကိုတောင်သွားသတိရမိသေးတယ်။မင်းသား Tobey Marshall က ပြိုင်ကားမောင်းနှင်လူသေမှုနဲ့ ထောင်ကျသွားပြီး ထောင်ကထွက်လာတဲ့အချိန်မှာ\r\nပြိုင်ကားမီးလောင်ပြီးသေသွားခဲ့တဲ့သူ့လူအတွက် ပြိုင်ကားမောင်းပြိုင်ပွဲအနေနဲ့ သူ့ရဲ့ပြိုင်ဘက် Dino ကို ပြန်လည်လက်တုံပြန်လက်စားချေတဲ့အခန်းဟာလည်း ပြိုင်ကားတွေကရှေ့ကပြေး ရဲကားတွေကနောက်ကလိုက်နဲ့ တော်တော်ကြည့်လို့ကောင်းပါတယ်။ နောက်ဆုံးဇာတ်သိမ်းပိုင်း မင်းသားက ရဲအဖမ်းခံလိုက်ရပေမယ့် သူ့ရဲ့သေသွားတဲ့ လုပ်ဖော်ကိုင်ဖက်အတွက် လက်တုံ့ပြန်နိုင်လိုက်လို့ ဝမ်းနည်းဝမ်းသာနဲ့ မျက်ရည်ကျတဲ့အခန်းဆို ကိုရီးယားကားကြည့်နေရတဲ့အတိုင်းပဲ။","year":2014,"imdb":6.4,"comment":true,"rating":4,"duration":"132 min","downloadas":"1","playas":"1","classification":"617 MB","image":"https://app.zchannelmovie.com/uploads/cache/poster_thumb/uploads/jpg/a52b456efdb2d02f74716b8f1802a11a.jpg","genres":[{"id":1,"title":"Action"}],"trailer":{"id":4488,"type":"youtube","url":"https://youtu.be/e73J71RZRn8"},"sources":[{"id":4487,"type":"mp4","url":"https://f002.backblazeb2.com/file/zstorage501/movies/2014/Need.For.Speed.2014.1080P.Bluray(msubmovie)(sd).mp4"}]},{"id":756,"type":"movie","title":"Night at the Museum: Secret of the Tomb","description":"၂၀၀၆ ကတည်းက စတင်အောင်မြင်ခဲ့တဲ့ အမေရိကန်ဟာသဇာတ်လမ်းရဲ့ တတိယမြောက် ဇာတ်လမ်းတွဲဖြစ်သလို နောက်ဆုံးဇာတ်လမ်းလည်းဖြစ်တဲ့ ဇာတ်ကားသစ်အကြောင်း ပြောပြချင်ပါတယ်။၁၉၃၈ တုန်းက ရှေးဟောင်းသုတေသနပညာရှင်အဖွဲ့ဟာ အဖိုးတန်ရှေးဟောင်းပစ္စည်းတစ်ခုကိုရှာဖွေဖို့ အီဂျစ်ဂူသင်္ချိုင်းတစ်ခုကို တူးဖော်ပါတယ်။ ဂူသင်္ချိုင်းထဲကိုကောင်လေးတစ်ယောက် ပြုတ်ကျရာကနေ သူ့ဖခင်နဲ့ အခြားရှေးဟောင်းသုတေသန ပညာရှင်တွေကို လမ်းကြောင်းရှာပေးနိုင်ခဲ့ပြီး ဖာရိုဘုရင်ရဲ့ ကမ္ပည်းထိုးထားတဲ့ရွှေချပ်ပြားကိုရှာတွေ့ခဲ့ပါတယ်။ အဲဒီနောက်တော့ ရွှေကမ္ပည်းပြားကို နှစ်ပေါင်းများစွာထိန်းသိမ်းထားပါတယ်။ယနေ့ခေတ် နယူးယောက်မြို့က သဘာဝသမိုင်းပြတိုက်ကြီးမှာ အခမ်းအနားကြီးတစ်ခုလုပ်နေပြီး ဒေါက်တာမက်ပီး တက်ရောက်လာတာကို ပြတိုက်လုံခြုံရေးဖြစ်တဲ့ လာရီဒါလေကတွေ့ပါတယ်။ Night at the Museum အရင်ဇာတ်ကားတွေအတိုင်းပဲ ပြတိုက်က အရုပ်တွေ အသက်ဝင်ပြီး သူတို့အသက်ရှင်စဉ်ကနေခဲ့တဲ့ ပုံစံအတိုင်းနေရင်း ပြတိုက်ထဲမှာ ဖြစ်ချင်တိုင်းဖြစ်နေပါတယ်။ အီဂျစ်ဂူသင်္ချိုင်းထဲက ရွှေကမ္ပည်းပြားက နယူးယောက်သဘာဝသမိုင်းပြတိုက်ထဲမှာ ထိန်းသိမ်းထားတာဖြစ်ပြီး အဲဒီပစ္စည်း တဖြည်းဖြည်းပျက်စီးလာတာကို ဘယ်သူမှ သတိမထားမိကြပါဘူး။ ကမ္ပည်းပြားကြောင့် အခမ်းအနား\r\nက ပရမ်းပတာတွေဖြစ်ပြီး ဧည့်သည်တွေကို တိုက်ခိုက်တာမျိုးတွေဖြစ်ပြီးတဲ့နောက် အရာအားလုံးတည်ငြိမ်သွားပေမယ့် ကမ္ပည်းပြားကြောင့်လို့တော့မသိခဲ့ကြပါဘူး။\r\nတစ်ရက်မှာ လာရီဟာ ပြသနာဖြစ်ရတဲ့အကြောင်းရင်းကို ရှာဖွေရင်း ပထမဆုံး ကမ္ပည်းပြားတွေ့တုန်းကပါသွားတဲ့ ကောင်လေးနဲ့ သူ့အဖေဓာတ်ပုံကို တွေ့ပြီး အဲဒီကောင်လေးဟာ ဆီ ဆဲဖရက်ဒရစ်ဆိုသူ ရွှေကမ္ပည်း ပြားခိုးယူဖို့ကြိုးစားတဲ့ ပြတိုက် လုံခြုံရေးဟောင်းဆိုတာ သိရပါတယ်။\r\nဆီဆဲဟာ အလုပ်က အနားယူပြီးဖြစ်တာကြောင့် သူနေတဲ့နေရာအထိ လိုက်သွားပြီး ကမ္ပည်းပြားအကြောင်းကို မေးမြန်းရင်း စုံစမ်းဖော်ထုတ်ဖို့ လုပ်ဆောင်ပါတယ်။\r\nလာရီတစ်ယောက် ရွှေကမ္ပည်း ပြားရဲ့ သမိုင်းကြောင်းကို စုံစမ်း ဖော်ထုတ်နိုင်မှာလား။ မှော်ဝင် ကမ္ပည်းပြားကြောင့် ဘယ်လိုအပြောင်းအလဲတွေ ဖြစ်ကုန်မလဲ ဆိုတာ……..။\r\n(ရုပ်ရှင်အညွှန်းကို 7Day Daily မှကူးယူဖော်ပြပါသည်။)","year":2014,"imdb":6.2,"comment":true,"rating":0,"duration":"98 min","downloadas":"1","playas":"1","classification":"1.12 GB","image":"https://app.zchannelmovie.com/uploads/cache/poster_thumb/uploads/jpg/ffadeb9a01a5a6b435e7d52fba2fa048.jpg","cover":"https://app.zchannelmovie.com/uploads/cache/cover_thumb/uploads/jpg/d63b7ece337eb00692d8cc4b3bb53557.jpg","genres":[{"id":2,"title":"Adventure"}],"trailer":{"id":4486,"type":"youtube","url":"https://youtu.be/Hr1fFMp0MqU"},"sources":[{"id":4485,"type":"mp4","url":"https://f002.backblazeb2.com/file/zstorage501/movies/2014/(zCM)Night.At.The.Museum.Secret.Of.The.Tomb.2014.1080P.Bluray(msubmovie)(hd).mp4"}]},{"id":755,"type":"movie","title":"Night at the Museum: Battle of the Smithsonian","description":"ပြတိုက်စောင့် Ben သည် ပြတိုက် ကို ညဘက်စောင့်သောအခါ ပြတိုက်ထဲတွင် ထားသော သမိုင်းဝင်အရုပ် များ၊ ဒိုင်နိုဆောအရုပ်များ ၊ လူပုလေးအရုပ် များ နှင့် အခြားများစွားသော အရုပ်များကြားတွင် ဘယ်လို ဇာတ်လမ်းဆက်မလဲ ဆိုတာကို ဝင်ရောက်ကြည့်ရှုနိုင်ပါသည်။ဒီ ဇာတ်လမ်းသည် Action, Adventure, Comedy, Fantasy, Family စသော ရသများကို ခံစားနိုင်ပြီး ဒါရိုက်တာ Shawn Levy ရိုက် ကူးထားသော ဇာတ်ကားကောင်း တစ်ကားဖြစ်ပါသည်………..","year":2009,"imdb":6,"comment":true,"rating":0,"duration":"105 min","downloadas":"1","playas":"1","classification":"2.38 GB","image":"https://app.zchannelmovie.com/uploads/cache/poster_thumb/uploads/jpg/cd79ac04091e4de7feb67608a5f6be57.jpg","genres":[{"id":2,"title":"Adventure"}],"trailer":{"id":4484,"type":"youtube","url":"https://youtu.be/QCR_fgG0ydY"},"sources":[{"id":4483,"type":"mkv","url":"https://f002.backblazeb2.com/file/zstorage501/movies/2009/(zCM)Night.At.The.Museum.Battle.Of.The.Smithsonian.2009.1080P.Bluray(msubmovie)(fhd).mkv"}]},{"id":754,"type":"movie","title":"Night at the Museum","description":"ညဘက်ဆို ရုပ်ထုတွေအသက်ဝင်လာတဲ့ဇာတ်ကားသုံးကားထဲက ဒီဇာတ်ကားက ၂၀၀၆ မှာထွက်ခဲ့တဲ့ ပထမဆုံးဇာတ်ကားဖြစ်ပါတယ်။ ကြည်ကြည်လင်လင်ပြန်ကြည့်ချင်သူတွေအတွက်တင်ပေးလိုက်ပါတယ်","year":2006,"imdb":6.4,"comment":true,"rating":0,"duration":"108 min","downloadas":"1","playas":"1","classification":"1.25 GB","image":"https://app.zchannelmovie.com/uploads/cache/poster_thumb/uploads/jpg/8f1fe7bef4a6c2b774ecfd0efbb570c4.jpg","genres":[{"id":2,"title":"Adventure"}],"trailer":{"id":4482,"type":"youtube","url":"https://youtu.be/YXu7kqD1JLs"},"sources":[{"id":4481,"type":"mp4","url":"https://f002.backblazeb2.com/file/zstorage501/movies/2006/(zCM)Night.At.The.Museum.2006.1080P.Bluray(msubmovie)(hd).mp4"}]},{"id":753,"type":"movie","title":"Bypass Road","description":"ဘောလီဝုဒ်ဖန်ကြီးအတွက် အသစ်ထွက်ရှိထားတဲ့ Mystery, Thriller ကားကောင်းတစ်ကားကို တင်ဆက်ပေးလိုက်ပါတယ်ခင်ဗျIMDb 5.6/10 အထိရရှိထားပါတယ်ဇာတ်လမ်းလေးကတော့ …ဖက်ရှိုးမန်နေဂျာတစ်ယောက်ဖြစ်တဲ့ ဗစ်ကရမ်ကပူးလ်ဟာဆိုးရွားတဲ့ကားတိုက်မှုတစ်ခုဖြစ်သွားပါတယ်\r\nထိုညမှာပဲ သူ့ဖက်ရှင်ရှိုးတွေက ဖက်ရှင်မော်ဒယ်တစ်ဦးဖြစ်သူ ဆာရာကလည်း သူ့ကိုယ်သူသတ်သေသွားပါတယ်တဲ့ဒါပေမဲ့ ရဲတပ်ဖွဲ့နဲ့ ဆာရာ့မိဘတွေကတော့ သူ့သမီးသတ်သေတာမဟုတ်ဘဲ အသတ်ခံရတာပါလို့ထွက်ဆိုထားပါတယ်ပြီးတော့ ဗစ်ကရမ်နဲ့ ဆာရာကလည်း ဇာတ်လမ်းမရှင်းရှင်းတွေထွက်ထားဖူးတာကြောင့် ဗစ်ကရမ်ကရော တကယ်ပဲ မတော်တဆဖြစ်ခဲ့တာလားလုပ်ကြံခံရတာလား ဆာရာကရော သူ့ကိုယ်သူသတ်သေခဲ့တာလားတစ်ယောက်ယောက်က သတ်ခဲ့တာလား ဒီကိစ္စတွေရဲ့နောက်ကွယ်မှာ ဘယ်သူရှိနေမလဲ …ဒါတွေကိုတော့ ဆက်လက်ကြည့်ရှု့ပြီး အဖြေထုတ်လိုက်ပါတော့ဇာတ်လမ်းအညွှန်းနဲ့ဘာသာပြန်သူကတော့ Zaw Htoo ပဲဖြစ်ပါတယ်…","year":2019,"imdb":5.4,"comment":true,"rating":0,"duration":"137 min","downloadas":"1","playas":"1","classification":"1.10 GB","image":"https://app.zchannelmovie.com/uploads/cache/poster_thumb/uploads/jpg/b9ea2754d7aee2cae252c24e04b61844.jpg","genres":[{"id":5,"title":"Horror & Thriller"},{"id":12,"title":"Bollywood (India)"}],"trailer":{"id":4480,"type":"youtube","url":"https://youtu.be/huXCTt-lYzs"},"sources":[{"id":4479,"type":"mp4","url":"https://f002.backblazeb2.com/file/zstorage501/movies/2019/(CM).Bypass.Road.2019.720p.NF.WEB.DL.mp4"}]}]